hdl/dpRAM/core_peripheric.v
// este periferico lee la dpRAM, obtieniendo asi los 6 primeros terminos de fibonnacci, luego los escribe de nuevo en la dpRAM en orden invertido;
module core_peripheric(clk, addr, d_in, d_out,  wr,  rd); 
	  
	input clk;
	input [15:0]d_in;

	output reg [15:0]d_out;
	output reg [7:0]addr; // 8 LSB from j1_io_addr
	output reg rd;
	output reg wr;

	reg [15:0] F_1, F_2, F_3, F_4, F_5, F_6; // aqui se almacenan los terminos de la serie de fibonacci
	reg [3:0] estado;

	initial begin
		d_out = 0;
		addr = 0;
		rd = 0;
		wr = 0;
		estado = 0;
		F_1 = 0;
		F_2 = 0;
		F_3 = 0;
		F_4 = 0;
		F_5 = 0;
		F_6 = 0;
	end

	always @(posedge clk) begin// definicion de la logica del estado  siguiente
		if (rd) begin
			case (addr)	 // lectura de los terminos de fibonnacci
				8'h00: F_1 = d_in;
				8'h02: F_2 = d_in;
				8'h04: F_3 = d_in;
				8'h06: F_4 = d_in;
				8'h08: F_5 = d_in;
				8'h0A: F_6 = d_in;
				default: F_1 = F_1;
			endcase
		end else 
			F_1 = F_1;

		case(estado)
			00: begin
				if (d_in == 13)	
					estado = 1;
				else 
					estado = 0;
				end
			01:  estado = 2;
			02:  estado = 3;
			03:  estado = 4;
			04:  estado = 5;
			05:  estado = 6;
			06:  estado = 7;
			07:  estado = 8;
			08:  estado = 9;
			09:  estado = 10;
			10:  estado = 11;
			11:  estado = 12;
			12:  estado = 13;
			13:  estado = 13;
			default: estado = 0;
		endcase
	end

	always @(*) begin// Definicion de las salidas
		case(estado)
			00: begin addr = 8'h0A; d_out = 16'h0000;  wr = 0;  rd = 1; end // lectura de los terminos de fibonnacci
			01: begin addr = 8'h00; d_out = 16'h0000;  wr = 0;  rd = 1; end
			02: begin addr = 8'h02; d_out = 16'h0000;  wr = 0;  rd = 1; end
			03: begin addr = 8'h04; d_out = 16'h0000;  wr = 0;  rd = 1; end
			04: begin addr = 8'h06; d_out = 16'h0000;  wr = 0;  rd = 1; end
			05: begin addr = 8'h08; d_out = 16'h0000;  wr = 0;  rd = 1; end
			06: begin addr = 8'h0A; d_out = 16'h0000;  wr = 0;  rd = 1; end

			07: begin addr = 8'h00; d_out = F_6;  wr = 1;  rd = 0; end // escritura de los terminos de fibonacci en orden invertido
			08: begin addr = 8'h02; d_out = F_5;  wr = 1;  rd = 0; end
			09: begin addr = 8'h04; d_out = F_4;  wr = 1;  rd = 0; end
			10: begin addr = 8'h06; d_out = F_3;  wr = 1;  rd = 0; end
			11: begin addr = 8'h08; d_out = F_2;  wr = 1;  rd = 0; end
			12: begin addr = 8'h0A; d_out = F_1;  wr = 1;  rd = 0; end

			13: begin addr = 8'h0A; d_out=16'h0000;  wr = 0;  rd = 0; end

			default: begin addr = 8'h00; d_out=16'h0000;  wr = 0;  rd = 0; end
		endcase
	end

endmodule

/*
  always @(negedge clk)
  begin
	if (addr==8'h0B)
		addr=0;
	else
		addr = addr+1;
  end

  reg [15:0] F_1, F_2, F_3, F_4, F_5, F_6; // aqui se almacenan los terminos de la serie de fibonacci


always @(posedge clk)
begin

      
      case (addr)
        8'h00: begin rd<=1;  F_1 <= d_in; end
        8'h02: begin rd<=1;  F_2 <= d_in; end
        8'h04: begin rd<=1;  F_3 <= d_in; end
        8'h06: begin rd<=1;  F_4 <= d_in; end
        8'h08: begin rd<=1;  F_5 <= d_in; end
        8'h0A: begin rd<=1;  F_6 <= d_in; end
	default: begin rd<=0;  end
      endcase

    if (F_6==8'h000D) begin
      case (addr)
        8'h00: begin d_out <= F_6; wr <= 1;  end
        8'h02: begin d_out <= F_5; wr <= 1;  end
        8'h04: begin d_out <= F_4; wr <= 1;  end
        8'h06: begin d_out <= F_3; wr <= 1;  end
        8'h08: begin d_out <= F_2; wr <= 1;  end
        8'h0A: begin d_out <= F_1; wr <= 1;  end
	default:  begin wr <= 0; end
      endcase
    end

end


endmodule
*/

hdl/dpRAM/dualport_RAM.v
module dualport_RAM(clk, d_in_1, d_out_1, addr_1, rd_1, wr_1, d_in_2, d_out_2, addr_2, rd_2, wr_2);
	  
	input clk;
	input [15:0]d_in_1;
	input [15:0]d_in_2;
	input [7:0]addr_1; // 8 LSB from address
	input [7:0]addr_2; // 8 LSB from address
	input rd_1;
	input wr_1;
	input rd_2;
	input wr_2;

	output reg [15:0]d_out_2 = 0;
	output reg [15:0]d_out_1 = 0;

	// Declare the RAM variable
	reg [15:0] ram [255:0]; // 256-bit x 8-bit RAM

	//------------------ port 1	: 	core J1---------------------
	always @(negedge clk)
		begin
		if (rd_1) begin
			d_out_1 <= ram[addr_1];
		end
		else if(wr_1) begin
			ram[addr_1] <= d_in_1;
		end
	end
	//------------------ port 1	: 	core J1---------------------
	
	//------------------ port 2	:	core peripheric-------------
	always @(negedge clk)
		begin
		/*else*/ 
		if (rd_2) begin
			d_out_2 <= ram[addr_2];
		end else if(wr_2) begin
			ram[addr_2] <= d_in_2;
		end
	end
	//------------------ port 2	:	core peripheric-------------
	
endmodule

hdl/dpRAM/dpRAM_interface.v
module dpRAM_interface(clk, addr, d_in, d_out, cs, wr, rd);
  
	input clk;
	input [15:0]d_in;
	input cs;
	input [7:0]addr; // 8 LSB from j1_io_addr
	input rd;
	input wr;
	
	output [15:0]d_out;

	//------------------------------------ regs and wires-------------------------------
	wire [15:0]d_in_p;
	wire [15:0]d_out_p;
	wire [7:0]addr_p; // 8 LSB from address
	wire rd_p;
	wire wr_p;
	//------------------------------------ regs and wires-------------------------------

	dualport_RAM dlptRAM (.clk(clk), .d_in_1(d_in), .d_out_1(d_out), .addr_1(addr), .rd_1(cs && rd), .wr_1(cs && wr), .d_in_2(d_in_p), .d_out_2(d_out_p), .addr_2(addr_p), .rd_2(rd_p), .wr_2(wr_p) );

	core_peripheric c_p ( .clk(clk), .addr(addr_p), .d_in(d_out_p), .d_out(d_in_p), .wr(wr_p), .rd(rd_p) );
	
endmodule

hdl/dpRAM/dpRAM_interface_TB.v
`timescale 1ns / 1ps

`define SIMULATION

module dpRAM_interface_TB;

	reg clk;
	reg [15:0]d_in;
	reg cs;
	reg [7:0]addr; // 8 LSB from j1_io_addr
	reg rd;
	reg wr;
	wire [15:0]d_out;
	
	parameter PERIOD = 20;
	parameter real DUTY_CYCLE = 0.5;
	parameter OFFSET = 0;
	
	reg [20:0] i;
	event reset_trigger;
		
	dpRAM_interface dpRAM(.clk(clk), .addr(addr), .d_in(d_in), .d_out(d_out), .cs(cs), .wr(wr), .rd(rd));
	
	initial begin// Initialize Inputs
		clk = 1;
		addr = 0;
		cs = 0;
		wr = 0;
		rd = 0;
		d_in = 0;
	end

	initial begin// Process for sys_clk_i
		#OFFSET;
		forever begin
			clk = 1'b0;
			#(PERIOD-(PERIOD*DUTY_CYCLE)) clk = 1'b1;
			#(PERIOD*DUTY_CYCLE);
		end
	end
	
	initial begin
		for(i = 0; i < 10000; i = i+1) begin
			@ (posedge clk);
			
			if(i == 20) begin
				addr = 8'h70;
				cs = 1;
				wr = 1;
				rd = 0;
				d_in = 4'hC;
			end
			
			if(i == 25) begin
				addr = 8'h70;
				cs = 1;
				wr = 0;
				rd = 1;
				d_in = 4'h0;
			end
			
			if(i == 30) begin
				addr = 8'h70;
				cs = 1;
				wr = 1;
				rd = 0;
				d_in = 4'hB;
			end
			
			if(i == 35) begin
				addr = 8'h70;
				cs = 1;
				wr = 0;
				rd = 1;
				d_in = 4'h0;
			end
			
		end
	end
	
	initial begin: TEST_CASE
	  	$dumpfile("dpRAM_interface_TB.vcd");
	  	$dumpvars(-1, dpRAM_interface_TB);
	
	  	#10 -> reset_trigger;
	  	#((PERIOD*DUTY_CYCLE)*10000) $finish;
	end

endmodule

hdl/dpRAM/simulation/dpRAM_interface_TB.vcd
$date
	Sun Jun 14 18:24:51 2015
$end
$version
	Icarus Verilog
$end
$timescale
	1ps
$end
$scope module dpRAM_interface_TB $end
$var event 1 ! reset_trigger $end
$var wire 16 " d_out [15:0] $end
$var reg 8 # addr [7:0] $end
$var reg 1 $ clk $end
$var reg 1 % cs $end
$var reg 16 & d_in [15:0] $end
$var reg 21 ' i [20:0] $end
$var reg 1 ( rd $end
$var reg 1 ) wr $end
$scope module dpRAM $end
$var wire 8 * addr [7:0] $end
$var wire 8 + addr_p [7:0] $end
$var wire 1 , clk $end
$var wire 1 - cs $end
$var wire 16 . d_in [15:0] $end
$var wire 16 / d_in_p [15:0] $end
$var wire 16 0 d_out [15:0] $end
$var wire 16 1 d_out_p [15:0] $end
$var wire 1 2 rd $end
$var wire 1 3 rd_p $end
$var wire 1 4 wr $end
$var wire 1 5 wr_p $end
$scope module dlptRAM $end
$var wire 8 6 addr_1 [7:0] $end
$var wire 8 7 addr_2 [7:0] $end
$var wire 1 , clk $end
$var wire 16 8 d_in_1 [15:0] $end
$var wire 16 9 d_in_2 [15:0] $end
$var wire 1 : rd_1 $end
$var wire 1 3 rd_2 $end
$var wire 1 ; wr_1 $end
$var wire 1 5 wr_2 $end
$var reg 16 < d_out_1 [15:0] $end
$var reg 16 = d_out_2 [15:0] $end
$upscope $end
$scope module c_p $end
$var wire 1 , clk $end
$var wire 16 > d_in [15:0] $end
$var reg 16 ? F_1 [15:0] $end
$var reg 16 @ F_2 [15:0] $end
$var reg 16 A F_3 [15:0] $end
$var reg 16 B F_4 [15:0] $end
$var reg 16 C F_5 [15:0] $end
$var reg 16 D F_6 [15:0] $end
$var reg 8 E addr [7:0] $end
$var reg 16 F d_out [15:0] $end
$var reg 4 G estado [3:0] $end
$var reg 1 H rd $end
$var reg 1 I wr $end
$upscope $end
$upscope $end
$scope begin TEST_CASE $end
$upscope $end
$upscope $end
$enddefinitions $end
#0
$dumpvars
0I
1H
b0 G
b0 F
b1010 E
b0 D
b0 C
b0 B
b0 A
b0 @
b0 ?
bx >
bx =
b0 <
0;
0:
b0 9
b0 8
b1010 7
b0 6
05
04
13
02
bx 1
b0 0
b0 /
b0 .
0-
0,
b1010 +
b0 *
0)
0(
b0 '
b0 &
0%
0$
b0 #
b0 "
1!
$end
#10000
b1 '
bx D
1$
1,
1!
#20000
0$
0,
#30000
b10 '
1$
1,
#40000
0$
0,
#50000
b11 '
1$
1,
#60000
0$
0,
#70000
b100 '
1$
1,
#80000
0$
0,
#90000
b101 '
1$
1,
#100000
0$
0,
#110000
b110 '
1$
1,
#120000
0$
0,
#130000
b111 '
1$
1,
#140000
0$
0,
#150000
b1000 '
1$
1,
#160000
0$
0,
#170000
b1001 '
1$
1,
#180000
0$
0,
#190000
b1010 '
1$
1,
#200000
0$
0,
#210000
b1011 '
1$
1,
#220000
0$
0,
#230000
b1100 '
1$
1,
#240000
0$
0,
#250000
b1101 '
1$
1,
#260000
0$
0,
#270000
b1110 '
1$
1,
#280000
0$
0,
#290000
b1111 '
1$
1,
#300000
0$
0,
#310000
b10000 '
1$
1,
#320000
0$
0,
#330000
b10001 '
1$
1,
#340000
0$
0,
#350000
b10010 '
1$
1,
#360000
0$
0,
#370000
b10011 '
1$
1,
#380000
0$
0,
#390000
b10100 '
1$
1,
#400000
0$
0,
#410000
1;
b10101 '
b1100 &
b1100 .
b1100 8
1)
14
1%
1-
b1110000 #
b1110000 *
b1110000 6
1$
1,
#420000
0$
0,
#430000
b10110 '
1$
1,
#440000
0$
0,
#450000
b10111 '
1$
1,
#460000
0$
0,
#470000
b11000 '
1$
1,
#480000
0$
0,
#490000
b11001 '
1$
1,
#500000
0$
0,
#510000
1:
0;
b11010 '
b0 &
b0 .
b0 8
1(
12
0)
04
1$
1,
#520000
b1100 <
b1100 "
b1100 0
0$
0,
#530000
b11011 '
1$
1,
#540000
0$
0,
#550000
b11100 '
1$
1,
#560000
0$
0,
#570000
b11101 '
1$
1,
#580000
0$
0,
#590000
b11110 '
1$
1,
#600000
0$
0,
#610000
0:
1;
b11111 '
b1011 &
b1011 .
b1011 8
0(
02
1)
14
1$
1,
#620000
0$
0,
#630000
b100000 '
1$
1,
#640000
0$
0,
#650000
b100001 '
1$
1,
#660000
0$
0,
#670000
b100010 '
1$
1,
#680000
0$
0,
#690000
b100011 '
1$
1,
#700000
0$
0,
#710000
1:
0;
b100100 '
b0 &
b0 .
b0 8
1(
12
0)
04
1$
1,
#720000
b1011 <
b1011 "
b1011 0
0$
0,
#730000
b100101 '
1$
1,
#740000
0$
0,
#750000
b100110 '
1$
1,
#760000
0$
0,
#770000
b100111 '
1$
1,
#780000
0$
0,
#790000
b101000 '
1$
1,
#800000
0$
0,
#810000
b101001 '
1$
1,
#820000
0$
0,
#830000
b101010 '
1$
1,
#840000
0$
0,
#850000
b101011 '
1$
1,
#860000
0$
0,
#870000
b101100 '
1$
1,
#880000
0$
0,
#890000
b101101 '
1$
1,
#900000
0$
0,
#910000
b101110 '
1$
1,
#920000
0$
0,
#930000
b101111 '
1$
1,
#940000
0$
0,
#950000
b110000 '
1$
1,
#960000
0$
0,
#970000
b110001 '
1$
1,
#980000
0$
0,
#990000
b110010 '
1$
1,
#1000000
0$
0,
#1010000
b110011 '
1$
1,
#1020000
0$
0,
#1030000
b110100 '
1$
1,
#1040000
0$
0,
#1050000
b110101 '
1$
1,
#1060000
0$
0,
#1070000
b110110 '
1$
1,
#1080000
0$
0,
#1090000
b110111 '
1$
1,
#1100000
0$
0,
#1110000
b111000 '
1$
1,
#1120000
0$
0,
#1130000
b111001 '
1$
1,
#1140000
0$
0,
#1150000
b111010 '
1$
1,
#1160000
0$
0,
#1170000
b111011 '
1$
1,
#1180000
0$
0,
#1190000
b111100 '
1$
1,
#1200000
0$
0,
#1210000
b111101 '
1$
1,
#1220000
0$
0,
#1230000
b111110 '
1$
1,
#1240000
0$
0,
#1250000
b111111 '
1$
1,
#1260000
0$
0,
#1270000
b1000000 '
1$
1,
#1280000
0$
0,
#1290000
b1000001 '
1$
1,
#1300000
0$
0,
#1310000
b1000010 '
1$
1,
#1320000
0$
0,
#1330000
b1000011 '
1$
1,
#1340000
0$
0,
#1350000
b1000100 '
1$
1,
#1360000
0$
0,
#1370000
b1000101 '
1$
1,
#1380000
0$
0,
#1390000
b1000110 '
1$
1,
#1400000
0$
0,
#1410000
b1000111 '
1$
1,
#1420000
0$
0,
#1430000
b1001000 '
1$
1,
#1440000
0$
0,
#1450000
b1001001 '
1$
1,
#1460000
0$
0,
#1470000
b1001010 '
1$
1,
#1480000
0$
0,
#1490000
b1001011 '
1$
1,
#1500000
0$
0,
#1510000
b1001100 '
1$
1,
#1520000
0$
0,
#1530000
b1001101 '
1$
1,
#1540000
0$
0,
#1550000
b1001110 '
1$
1,
#1560000
0$
0,
#1570000
b1001111 '
1$
1,
#1580000
0$
0,
#1590000
b1010000 '
1$
1,
#1600000
0$
0,
#1610000
b1010001 '
1$
1,
#1620000
0$
0,
#1630000
b1010010 '
1$
1,
#1640000
0$
0,
#1650000
b1010011 '
1$
1,
#1660000
0$
0,
#1670000
b1010100 '
1$
1,
#1680000
0$
0,
#1690000
b1010101 '
1$
1,
#1700000
0$
0,
#1710000
b1010110 '
1$
1,
#1720000
0$
0,
#1730000
b1010111 '
1$
1,
#1740000
0$
0,
#1750000
b1011000 '
1$
1,
#1760000
0$
0,
#1770000
b1011001 '
1$
1,
#1780000
0$
0,
#1790000
b1011010 '
1$
1,
#1800000
0$
0,
#1810000
b1011011 '
1$
1,
#1820000
0$
0,
#1830000
b1011100 '
1$
1,
#1840000
0$
0,
#1850000
b1011101 '
1$
1,
#1860000
0$
0,
#1870000
b1011110 '
1$
1,
#1880000
0$
0,
#1890000
b1011111 '
1$
1,
#1900000
0$
0,
#1910000
b1100000 '
1$
1,
#1920000
0$
0,
#1930000
b1100001 '
1$
1,
#1940000
0$
0,
#1950000
b1100010 '
1$
1,
#1960000
0$
0,
#1970000
b1100011 '
1$
1,
#1980000
0$
0,
#1990000
b1100100 '
1$
1,
#2000000
0$
0,
#2010000
b1100101 '
1$
1,
#2020000
0$
0,
#2030000
b1100110 '
1$
1,
#2040000
0$
0,
#2050000
b1100111 '
1$
1,
#2060000
0$
0,
#2070000
b1101000 '
1$
1,
#2080000
0$
0,
#2090000
b1101001 '
1$
1,
#2100000
0$
0,
#2110000
b1101010 '
1$
1,
#2120000
0$
0,
#2130000
b1101011 '
1$
1,
#2140000
0$
0,
#2150000
b1101100 '
1$
1,
#2160000
0$
0,
#2170000
b1101101 '
1$
1,
#2180000
0$
0,
#2190000
b1101110 '
1$
1,
#2200000
0$
0,
#2210000
b1101111 '
1$
1,
#2220000
0$
0,
#2230000
b1110000 '
1$
1,
#2240000
0$
0,
#2250000
b1110001 '
1$
1,
#2260000
0$
0,
#2270000
b1110010 '
1$
1,
#2280000
0$
0,
#2290000
b1110011 '
1$
1,
#2300000
0$
0,
#2310000
b1110100 '
1$
1,
#2320000
0$
0,
#2330000
b1110101 '
1$
1,
#2340000
0$
0,
#2350000
b1110110 '
1$
1,
#2360000
0$
0,
#2370000
b1110111 '
1$
1,
#2380000
0$
0,
#2390000
b1111000 '
1$
1,
#2400000
0$
0,
#2410000
b1111001 '
1$
1,
#2420000
0$
0,
#2430000
b1111010 '
1$
1,
#2440000
0$
0,
#2450000
b1111011 '
1$
1,
#2460000
0$
0,
#2470000
b1111100 '
1$
1,
#2480000
0$
0,
#2490000
b1111101 '
1$
1,
#2500000
0$
0,
#2510000
b1111110 '
1$
1,
#2520000
0$
0,
#2530000
b1111111 '
1$
1,
#2540000
0$
0,
#2550000
b10000000 '
1$
1,
#2560000
0$
0,
#2570000
b10000001 '
1$
1,
#2580000
0$
0,
#2590000
b10000010 '
1$
1,
#2600000
0$
0,
#2610000
b10000011 '
1$
1,
#2620000
0$
0,
#2630000
b10000100 '
1$
1,
#2640000
0$
0,
#2650000
b10000101 '
1$
1,
#2660000
0$
0,
#2670000
b10000110 '
1$
1,
#2680000
0$
0,
#2690000
b10000111 '
1$
1,
#2700000
0$
0,
#2710000
b10001000 '
1$
1,
#2720000
0$
0,
#2730000
b10001001 '
1$
1,
#2740000
0$
0,
#2750000
b10001010 '
1$
1,
#2760000
0$
0,
#2770000
b10001011 '
1$
1,
#2780000
0$
0,
#2790000
b10001100 '
1$
1,
#2800000
0$
0,
#2810000
b10001101 '
1$
1,
#2820000
0$
0,
#2830000
b10001110 '
1$
1,
#2840000
0$
0,
#2850000
b10001111 '
1$
1,
#2860000
0$
0,
#2870000
b10010000 '
1$
1,
#2880000
0$
0,
#2890000
b10010001 '
1$
1,
#2900000
0$
0,
#2910000
b10010010 '
1$
1,
#2920000
0$
0,
#2930000
b10010011 '
1$
1,
#2940000
0$
0,
#2950000
b10010100 '
1$
1,
#2960000
0$
0,
#2970000
b10010101 '
1$
1,
#2980000
0$
0,
#2990000
b10010110 '
1$
1,
#3000000
0$
0,
#3010000
b10010111 '
1$
1,
#3020000
0$
0,
#3030000
b10011000 '
1$
1,
#3040000
0$
0,
#3050000
b10011001 '
1$
1,
#3060000
0$
0,
#3070000
b10011010 '
1$
1,
#3080000
0$
0,
#3090000
b10011011 '
1$
1,
#3100000
0$
0,
#3110000
b10011100 '
1$
1,
#3120000
0$
0,
#3130000
b10011101 '
1$
1,
#3140000
0$
0,
#3150000
b10011110 '
1$
1,
#3160000
0$
0,
#3170000
b10011111 '
1$
1,
#3180000
0$
0,
#3190000
b10100000 '
1$
1,
#3200000
0$
0,
#3210000
b10100001 '
1$
1,
#3220000
0$
0,
#3230000
b10100010 '
1$
1,
#3240000
0$
0,
#3250000
b10100011 '
1$
1,
#3260000
0$
0,
#3270000
b10100100 '
1$
1,
#3280000
0$
0,
#3290000
b10100101 '
1$
1,
#3300000
0$
0,
#3310000
b10100110 '
1$
1,
#3320000
0$
0,
#3330000
b10100111 '
1$
1,
#3340000
0$
0,
#3350000
b10101000 '
1$
1,
#3360000
0$
0,
#3370000
b10101001 '
1$
1,
#3380000
0$
0,
#3390000
b10101010 '
1$
1,
#3400000
0$
0,
#3410000
b10101011 '
1$
1,
#3420000
0$
0,
#3430000
b10101100 '
1$
1,
#3440000
0$
0,
#3450000
b10101101 '
1$
1,
#3460000
0$
0,
#3470000
b10101110 '
1$
1,
#3480000
0$
0,
#3490000
b10101111 '
1$
1,
#3500000
0$
0,
#3510000
b10110000 '
1$
1,
#3520000
0$
0,
#3530000
b10110001 '
1$
1,
#3540000
0$
0,
#3550000
b10110010 '
1$
1,
#3560000
0$
0,
#3570000
b10110011 '
1$
1,
#3580000
0$
0,
#3590000
b10110100 '
1$
1,
#3600000
0$
0,
#3610000
b10110101 '
1$
1,
#3620000
0$
0,
#3630000
b10110110 '
1$
1,
#3640000
0$
0,
#3650000
b10110111 '
1$
1,
#3660000
0$
0,
#3670000
b10111000 '
1$
1,
#3680000
0$
0,
#3690000
b10111001 '
1$
1,
#3700000
0$
0,
#3710000
b10111010 '
1$
1,
#3720000
0$
0,
#3730000
b10111011 '
1$
1,
#3740000
0$
0,
#3750000
b10111100 '
1$
1,
#3760000
0$
0,
#3770000
b10111101 '
1$
1,
#3780000
0$
0,
#3790000
b10111110 '
1$
1,
#3800000
0$
0,
#3810000
b10111111 '
1$
1,
#3820000
0$
0,
#3830000
b11000000 '
1$
1,
#3840000
0$
0,
#3850000
b11000001 '
1$
1,
#3860000
0$
0,
#3870000
b11000010 '
1$
1,
#3880000
0$
0,
#3890000
b11000011 '
1$
1,
#3900000
0$
0,
#3910000
b11000100 '
1$
1,
#3920000
0$
0,
#3930000
b11000101 '
1$
1,
#3940000
0$
0,
#3950000
b11000110 '
1$
1,
#3960000
0$
0,
#3970000
b11000111 '
1$
1,
#3980000
0$
0,
#3990000
b11001000 '
1$
1,
#4000000
0$
0,
#4010000
b11001001 '
1$
1,
#4020000
0$
0,
#4030000
b11001010 '
1$
1,
#4040000
0$
0,
#4050000
b11001011 '
1$
1,
#4060000
0$
0,
#4070000
b11001100 '
1$
1,
#4080000
0$
0,
#4090000
b11001101 '
1$
1,
#4100000
0$
0,
#4110000
b11001110 '
1$
1,
#4120000
0$
0,
#4130000
b11001111 '
1$
1,
#4140000
0$
0,
#4150000
b11010000 '
1$
1,
#4160000
0$
0,
#4170000
b11010001 '
1$
1,
#4180000
0$
0,
#4190000
b11010010 '
1$
1,
#4200000
0$
0,
#4210000
b11010011 '
1$
1,
#4220000
0$
0,
#4230000
b11010100 '
1$
1,
#4240000
0$
0,
#4250000
b11010101 '
1$
1,
#4260000
0$
0,
#4270000
b11010110 '
1$
1,
#4280000
0$
0,
#4290000
b11010111 '
1$
1,
#4300000
0$
0,
#4310000
b11011000 '
1$
1,
#4320000
0$
0,
#4330000
b11011001 '
1$
1,
#4340000
0$
0,
#4350000
b11011010 '
1$
1,
#4360000
0$
0,
#4370000
b11011011 '
1$
1,
#4380000
0$
0,
#4390000
b11011100 '
1$
1,
#4400000
0$
0,
#4410000
b11011101 '
1$
1,
#4420000
0$
0,
#4430000
b11011110 '
1$
1,
#4440000
0$
0,
#4450000
b11011111 '
1$
1,
#4460000
0$
0,
#4470000
b11100000 '
1$
1,
#4480000
0$
0,
#4490000
b11100001 '
1$
1,
#4500000
0$
0,
#4510000
b11100010 '
1$
1,
#4520000
0$
0,
#4530000
b11100011 '
1$
1,
#4540000
0$
0,
#4550000
b11100100 '
1$
1,
#4560000
0$
0,
#4570000
b11100101 '
1$
1,
#4580000
0$
0,
#4590000
b11100110 '
1$
1,
#4600000
0$
0,
#4610000
b11100111 '
1$
1,
#4620000
0$
0,
#4630000
b11101000 '
1$
1,
#4640000
0$
0,
#4650000
b11101001 '
1$
1,
#4660000
0$
0,
#4670000
b11101010 '
1$
1,
#4680000
0$
0,
#4690000
b11101011 '
1$
1,
#4700000
0$
0,
#4710000
b11101100 '
1$
1,
#4720000
0$
0,
#4730000
b11101101 '
1$
1,
#4740000
0$
0,
#4750000
b11101110 '
1$
1,
#4760000
0$
0,
#4770000
b11101111 '
1$
1,
#4780000
0$
0,
#4790000
b11110000 '
1$
1,
#4800000
0$
0,
#4810000
b11110001 '
1$
1,
#4820000
0$
0,
#4830000
b11110010 '
1$
1,
#4840000
0$
0,
#4850000
b11110011 '
1$
1,
#4860000
0$
0,
#4870000
b11110100 '
1$
1,
#4880000
0$
0,
#4890000
b11110101 '
1$
1,
#4900000
0$
0,
#4910000
b11110110 '
1$
1,
#4920000
0$
0,
#4930000
b11110111 '
1$
1,
#4940000
0$
0,
#4950000
b11111000 '
1$
1,
#4960000
0$
0,
#4970000
b11111001 '
1$
1,
#4980000
0$
0,
#4990000
b11111010 '
1$
1,
#5000000
0$
0,
#5010000
b11111011 '
1$
1,
#5020000
0$
0,
#5030000
b11111100 '
1$
1,
#5040000
0$
0,
#5050000
b11111101 '
1$
1,
#5060000
0$
0,
#5070000
b11111110 '
1$
1,
#5080000
0$
0,
#5090000
b11111111 '
1$
1,
#5100000
0$
0,
#5110000
b100000000 '
1$
1,
#5120000
0$
0,
#5130000
b100000001 '
1$
1,
#5140000
0$
0,
#5150000
b100000010 '
1$
1,
#5160000
0$
0,
#5170000
b100000011 '
1$
1,
#5180000
0$
0,
#5190000
b100000100 '
1$
1,
#5200000
0$
0,
#5210000
b100000101 '
1$
1,
#5220000
0$
0,
#5230000
b100000110 '
1$
1,
#5240000
0$
0,
#5250000
b100000111 '
1$
1,
#5260000
0$
0,
#5270000
b100001000 '
1$
1,
#5280000
0$
0,
#5290000
b100001001 '
1$
1,
#5300000
0$
0,
#5310000
b100001010 '
1$
1,
#5320000
0$
0,
#5330000
b100001011 '
1$
1,
#5340000
0$
0,
#5350000
b100001100 '
1$
1,
#5360000
0$
0,
#5370000
b100001101 '
1$
1,
#5380000
0$
0,
#5390000
b100001110 '
1$
1,
#5400000
0$
0,
#5410000
b100001111 '
1$
1,
#5420000
0$
0,
#5430000
b100010000 '
1$
1,
#5440000
0$
0,
#5450000
b100010001 '
1$
1,
#5460000
0$
0,
#5470000
b100010010 '
1$
1,
#5480000
0$
0,
#5490000
b100010011 '
1$
1,
#5500000
0$
0,
#5510000
b100010100 '
1$
1,
#5520000
0$
0,
#5530000
b100010101 '
1$
1,
#5540000
0$
0,
#5550000
b100010110 '
1$
1,
#5560000
0$
0,
#5570000
b100010111 '
1$
1,
#5580000
0$
0,
#5590000
b100011000 '
1$
1,
#5600000
0$
0,
#5610000
b100011001 '
1$
1,
#5620000
0$
0,
#5630000
b100011010 '
1$
1,
#5640000
0$
0,
#5650000
b100011011 '
1$
1,
#5660000
0$
0,
#5670000
b100011100 '
1$
1,
#5680000
0$
0,
#5690000
b100011101 '
1$
1,
#5700000
0$
0,
#5710000
b100011110 '
1$
1,
#5720000
0$
0,
#5730000
b100011111 '
1$
1,
#5740000
0$
0,
#5750000
b100100000 '
1$
1,
#5760000
0$
0,
#5770000
b100100001 '
1$
1,
#5780000
0$
0,
#5790000
b100100010 '
1$
1,
#5800000
0$
0,
#5810000
b100100011 '
1$
1,
#5820000
0$
0,
#5830000
b100100100 '
1$
1,
#5840000
0$
0,
#5850000
b100100101 '
1$
1,
#5860000
0$
0,
#5870000
b100100110 '
1$
1,
#5880000
0$
0,
#5890000
b100100111 '
1$
1,
#5900000
0$
0,
#5910000
b100101000 '
1$
1,
#5920000
0$
0,
#5930000
b100101001 '
1$
1,
#5940000
0$
0,
#5950000
b100101010 '
1$
1,
#5960000
0$
0,
#5970000
b100101011 '
1$
1,
#5980000
0$
0,
#5990000
b100101100 '
1$
1,
#6000000
0$
0,
#6010000
b100101101 '
1$
1,
#6020000
0$
0,
#6030000
b100101110 '
1$
1,
#6040000
0$
0,
#6050000
b100101111 '
1$
1,
#6060000
0$
0,
#6070000
b100110000 '
1$
1,
#6080000
0$
0,
#6090000
b100110001 '
1$
1,
#6100000
0$
0,
#6110000
b100110010 '
1$
1,
#6120000
0$
0,
#6130000
b100110011 '
1$
1,
#6140000
0$
0,
#6150000
b100110100 '
1$
1,
#6160000
0$
0,
#6170000
b100110101 '
1$
1,
#6180000
0$
0,
#6190000
b100110110 '
1$
1,
#6200000
0$
0,
#6210000
b100110111 '
1$
1,
#6220000
0$
0,
#6230000
b100111000 '
1$
1,
#6240000
0$
0,
#6250000
b100111001 '
1$
1,
#6260000
0$
0,
#6270000
b100111010 '
1$
1,
#6280000
0$
0,
#6290000
b100111011 '
1$
1,
#6300000
0$
0,
#6310000
b100111100 '
1$
1,
#6320000
0$
0,
#6330000
b100111101 '
1$
1,
#6340000
0$
0,
#6350000
b100111110 '
1$
1,
#6360000
0$
0,
#6370000
b100111111 '
1$
1,
#6380000
0$
0,
#6390000
b101000000 '
1$
1,
#6400000
0$
0,
#6410000
b101000001 '
1$
1,
#6420000
0$
0,
#6430000
b101000010 '
1$
1,
#6440000
0$
0,
#6450000
b101000011 '
1$
1,
#6460000
0$
0,
#6470000
b101000100 '
1$
1,
#6480000
0$
0,
#6490000
b101000101 '
1$
1,
#6500000
0$
0,
#6510000
b101000110 '
1$
1,
#6520000
0$
0,
#6530000
b101000111 '
1$
1,
#6540000
0$
0,
#6550000
b101001000 '
1$
1,
#6560000
0$
0,
#6570000
b101001001 '
1$
1,
#6580000
0$
0,
#6590000
b101001010 '
1$
1,
#6600000
0$
0,
#6610000
b101001011 '
1$
1,
#6620000
0$
0,
#6630000
b101001100 '
1$
1,
#6640000
0$
0,
#6650000
b101001101 '
1$
1,
#6660000
0$
0,
#6670000
b101001110 '
1$
1,
#6680000
0$
0,
#6690000
b101001111 '
1$
1,
#6700000
0$
0,
#6710000
b101010000 '
1$
1,
#6720000
0$
0,
#6730000
b101010001 '
1$
1,
#6740000
0$
0,
#6750000
b101010010 '
1$
1,
#6760000
0$
0,
#6770000
b101010011 '
1$
1,
#6780000
0$
0,
#6790000
b101010100 '
1$
1,
#6800000
0$
0,
#6810000
b101010101 '
1$
1,
#6820000
0$
0,
