hdl/uart/uart.v
module uart(clk, rst, init_tx, init_rx ,uart_data_in, uart_tx, uart_tx_busy, uart_data_out, uart_rx, uart_rx_busy, done);

	//--------------------Entradas
	input clk;
	input rst;
	
	input init_tx;
	input init_rx;
	
	input [7:0]uart_data_in;
	input uart_rx;
	
	//--------------------Salidas
	output reg [7:0]uart_data_out;
	
	output uart_tx;
	
	output uart_tx_busy;
	output uart_rx_busy;	
	
	output done;
	
	//--------------------Variables facilitadoras
	reg [3:0]bitcount_rx;
	reg [3:0]bitcount_tx;
	
	wire uart_rx;
	wire uart_rx_busy = |bitcount_rx;
	wire receiving = |bitcount_rx[3:1];
	
	reg uart_tx;
	wire uart_tx_busy = |bitcount_tx; // invertidos v
	wire sending = |bitcount_tx[3:1]; // invertidos ^

	reg [8:0]shifter;
	
	wire done = receiving ^ uart_rx_busy;
	
	//--------------------clk is 50MHz (Nexys2). We want a 115200Hz clock.
	reg [28:0] d;
	wire [28:0] dInc = d[28] ? (115200) : (115200 - 50000000); // Si el último bit es 1, reinicia el contador, si es 0, lo deja a 115200 de volverse 1.
	wire [28:0] dNxt = d + dInc;
	wire clk_div = ~d[28]; // Pulso resultante resultante.

	always @(posedge clk)
		if (rst) begin
			d = 0;
		end else begin
			d = dNxt;
		end
	
	always @(posedge clk) begin
		if (rst) begin
			uart_tx <= 1;
			bitcount_tx <= 0;
			shifter <= 0;
			
			uart_data_out <= 0;
			bitcount_rx <= 0;
		end else begin
			//--------------------Tx UART
			if (~sending & ~receiving & init_tx) begin
				shifter <= { uart_data_in , 1'h0 }; // Marca el bit de inicio.
				bitcount_tx <= (1 + 8 + 2); // Para contar 1bit de inicio (low) de transmisión, contar el número de bits a enviar y mantener 2bits en alto para terminar.
			end

			if (uart_tx_busy & clk_div) begin
				// { 8:0 , 1 } <= { 1 , 8:0 } -> { 110110110 , 0 } <= { 1 , 101101100 } -> { 111011011 , 0 } <= { 1 , 110110110 }
				{ shifter , uart_tx } <= { 1'h1 , shifter }; 
				bitcount_tx <= bitcount_tx - 1;
			end
			
			//--------------------Rx UART
			if(~sending & ~receiving & ~uart_rx & init_rx) begin
				bitcount_rx <= 10;
				uart_data_out <= 0;
			end
		
			if(uart_rx_busy & clk_div) begin
				bitcount_rx <= bitcount_rx - 1;
				
				if(receiving) begin
					uart_data_out <= { uart_rx , uart_data_out[7:1]}; //Revisar, está lleyendo al revés.
				end
			end			
		end
	end
endmodule

hdl/uart/peripheral_uart.v
module peripheral_uart(clk, rst, addr, cs, rd, wr, data_in, uart_tx, tx_led, data_out, uart_rx, rx_led);

	//--------------------Entradas
	input clk;
	input rst;
	
	input cs;
	input rd;
	input wr;
	
	input [3:0]addr;
	input [15:0]data_in;
	input uart_rx;

	//--------------------Salidas
	output reg [15:0]data_out;
	output uart_tx;
	
	output reg rx_led;
	output reg tx_led;
	
	//--------------------Intermediarias
	reg [3:0] sel_mux;
	reg [7:0] uart_data_in;
	reg init_tx;
	reg init_rx;
	
	wire [7:0]uart_data_out;
	wire uart_rx_busy;
	wire uart_tx_busy;
	wire uart_done;
	
	//--------------------Decodificador de direcciones
	always @(*) begin
		case (addr)
			4'h0: sel_mux = (cs && wr) ? 4'h1 : 4'b0; // Escritura de datos de entrada.
			4'h2: sel_mux = (cs && rd) ? 4'h2 : 4'b0; // Lectura de datos de salida.
			4'h4: sel_mux = (cs && rd) ? 4'h4 : 4'b0; // Lectura de estado de transmisión.
			4'h6: sel_mux = (cs && rd) ? 4'h6 : 4'b0; // Lectura de estado de recepción.
			4'h8: sel_mux = (cs && wr) ? 4'h8 : 4'b0; // Iniciar tx.
			4'hA: sel_mux = (cs && rd) ? 4'hA : 4'b0; // Iniciar rx.
			4'hB: sel_mux = (cs && rd) ? 4'hB : 4'b0; // Leer done.
			default: sel_mux = 4'b0;
		endcase
	end

	//--------------------Control de entrada a la UART
	always @(negedge clk) begin
		tx_led = uart_tx_busy;
		rx_led = uart_rx_busy;
		uart_data_in = sel_mux[0] ? data_in[7:0] : uart_data_in;
		init_tx = (~sel_mux[1] & sel_mux[3]) ? 1 : 0;
		init_rx = (sel_mux[1] & sel_mux[3]) ? ~uart_rx_busy : ~uart_rx_busy & init_rx;
	end

	//--------------------Control de salida de la UART
	always @(negedge clk) begin
		case (sel_mux)
			4'h2: data_out = uart_data_out;
			4'h4: data_out = uart_tx_busy;
			4'h6: data_out = uart_rx_busy;
			4'hB: data_out = uart_done;
			default: data_out = uart_data_out;
		endcase
	end

	uart uart(.clk(clk), .rst(rst), .init_tx(init_tx), .init_rx(init_rx), .uart_data_in(uart_data_in), .uart_tx(uart_tx), .uart_tx_busy(uart_tx_busy), .uart_data_out(uart_data_out), .uart_rx(uart_rx), .uart_rx_busy(uart_rx_busy), .done(uart_done));

endmodule

hdl/uart/peripheral_uart_TB.v
`timescale 1ns / 1ps

`define SIMULATION

module peripheral_uart_TB;

	reg clk;
	reg rst;
	
	reg cs;
	reg rd;
	reg wr;
	
	reg [3:0]addr;
	reg [15:0]data_in;
	reg uart_rx;
	
	//--------------------Salidas
	wire [15:0]data_out;
	wire uart_tx;
	
	wire tx_busy;
	wire rx_busy;
	
	wire rx_led;
	wire tx_led;
	
	//--------------------Generar reloj
	parameter PERIOD = 20;
	parameter real DUTY_CYCLE = 0.5;
	parameter OFFSET = 0;
	
	reg [20:0] i;
	reg [20:0] fac;
	event reset_trigger;
		
	peripheral_uart p_uart(.clk(clk) , .rst(rst), .addr(addr), .cs(cs), .rd(rd), .wr(wr), .data_in(data_in), .uart_tx(uart_tx), .tx_led(tx_led), .data_out(data_out), .uart_rx(uart_rx), .rx_led(rx_led));
	
	initial begin// Initialize Inputs
		clk = 1;
		rst = 1;
		data_in = 0;
		cs = 0;
		addr = 3'b000;
		rd = 0;
		wr = 0;
		
		uart_rx=1;
		
		fac = 1;
	end

	initial begin// Process for sys_clk_i
		#OFFSET;
		forever begin
			clk = 1'b0;
			#(PERIOD-(PERIOD*DUTY_CYCLE)) clk = 1'b1;
			#(PERIOD*DUTY_CYCLE);
		end
	end
	
	initial begin
		for(i = 0; i < 30000; i = i+1) begin
			@ (posedge clk);
			
			if(i == 10) begin
				rst = 0;
			end
			
			//--------------------Envia EE = 11101110
			if(i == 15) begin
				addr = 4'h0;
				cs = 1;
				rd = 0;
				wr = 1;
				data_in = 8'hEE;
			end
			
			if(i == 20) begin
				addr = 4'h8;
				cs = 1;
				rd = 0;
				wr = 1;
				data_in = 0;
			end
			
			if(i == 25) begin
				addr = 4'hC;
				cs = 0;
				rd = 0;
				wr = 0;
				data_in = 0;
			end
			
			//--------------------Envia C2 = 11000010
			if(i == 6000) begin
				addr = 4'h0;
				cs = 1;
				rd = 0;
				wr = 1;
				data_in = 8'hC2;
			end
			
			if(i == 6005) begin
				addr = 4'h8;
				cs = 1;
				rd = 0;
				wr = 1;
				data_in = 0;
			end
			
			if(i == 6015) begin
				addr = 4'hC;
				cs = 1;
				rd = 0;
				wr = 0;
			end
			
			//--------------------Iniciar escucha.
			if(i == 11000+fac) begin
				addr = 4'hA;	
				cs = 1;
				rd = 1;
				wr = 0;
			end
			
			if(i == 11005+fac) begin
				addr = 4'hC;	
				cs = 1;
				rd = 0;
				wr = 0;
			end
			
			//--------------------Rx 10101110 = AE			
			if(i == 11520+fac) begin
				uart_rx = 0; // inicio de recepción
			end
			
			if(i == 11954+fac) begin
				uart_rx = 0;
			end
			
			if(i == 12388+fac) begin
				uart_rx = 1;
			end
			
			if(i == 12822+fac) begin
				uart_rx = 1;
			end
			
			if(i == 13256+fac) begin
				uart_rx = 1;
			end
			
			if(i == 13690+fac) begin
				uart_rx = 0;
			end
			
			if(i == 14124+fac) begin
				uart_rx = 1;
			end
			
			if(i == 14558+fac) begin
				uart_rx = 0;
			end
			
			if(i == 14992+fac) begin
				uart_rx = 1;
			end
			// end
			if(i == 15426+fac) begin
				uart_rx = 1;
			end
			
			//--------------------Iniciar escucha.
			if(i == 20000) begin
				addr = 4'h2;
				cs = 1;
				rd = 1;
				wr = 0;
			end
			
		end
	end
	
	initial begin: TEST_CASE
	  	$dumpfile("peripheral_uart_TB.vcd");
	  	$dumpvars(-1, peripheral_uart_TB);
	
	  	#10 -> reset_trigger;
	  	#((PERIOD*DUTY_CYCLE)*60000) $finish;
	end

endmodule

hdl/uart/simulation/peripheral_uart_TB.vcd
$date
	Thu Jun 18 22:45:29 2015
$end
$version
	Icarus Verilog
$end
$timescale
	1ps
$end
$scope module peripheral_uart_TB $end
$var event 1 ! reset_trigger $end
$var wire 16 " data_out [15:0] $end
$var wire 1 # rx_led $end
$var wire 1 $ tx_led $end
$var wire 1 % uart_tx $end
$var reg 4 & addr [3:0] $end
$var reg 1 ' clk $end
$var reg 1 ( cs $end
$var reg 16 ) data_in [15:0] $end
$var reg 21 * fac [20:0] $end
$var reg 21 + i [20:0] $end
$var reg 1 , rd $end
$var reg 1 - rst $end
$var reg 1 . uart_rx $end
$var reg 1 / wr $end
$scope module p_uart $end
$var wire 4 0 addr [3:0] $end
$var wire 1 1 clk $end
$var wire 1 2 cs $end
$var wire 16 3 data_in [15:0] $end
$var wire 1 4 rd $end
$var wire 1 5 rst $end
$var wire 8 6 uart_data_out [7:0] $end
$var wire 1 7 uart_done $end
$var wire 1 8 uart_rx $end
$var wire 1 9 uart_rx_busy $end
$var wire 1 % uart_tx $end
$var wire 1 : uart_tx_busy $end
$var wire 1 ; wr $end
$var reg 16 < data_out [15:0] $end
$var reg 1 = init_rx $end
$var reg 1 > init_tx $end
$var reg 1 ? rx_led $end
$var reg 4 @ sel_mux [3:0] $end
$var reg 1 A tx_led $end
$var reg 8 B uart_data_in [7:0] $end
$scope module uart $end
$var wire 1 1 clk $end
$var wire 1 C clk_div $end
$var wire 29 D dInc [28:0] $end
$var wire 29 E dNxt [28:0] $end
$var wire 1 7 done $end
$var wire 1 F init_rx $end
$var wire 1 G init_tx $end
$var wire 1 H receiving $end
$var wire 1 5 rst $end
$var wire 1 I sending $end
$var wire 8 J uart_data_in [7:0] $end
$var wire 1 8 uart_rx $end
$var wire 1 9 uart_rx_busy $end
$var wire 1 : uart_tx_busy $end
$var reg 4 K bitcount_rx [3:0] $end
$var reg 4 L bitcount_tx [3:0] $end
$var reg 29 M d [28:0] $end
$var reg 9 N shifter [8:0] $end
$var reg 8 O uart_data_out [7:0] $end
$var reg 1 P uart_tx $end
$upscope $end
$upscope $end
$scope begin TEST_CASE $end
$upscope $end
$upscope $end
$enddefinitions $end
#0
$dumpvars
1P
b0 O
b0 N
b0 M
b0 L
b0 K
bx J
0I
0H
0G
xF
b11101000001101101000110000000 E
b11101000001101101000110000000 D
1C
bx B
xA
b0 @
x?
0>
x=
b0xxxxxxxx <
0;
0:
09
18
07
b0 6
15
04
b0 3
02
01
b0 0
0/
1.
1-
0,
b0 +
b1 *
b0 )
0(
0'
b0 &
1%
x$
x#
b0xxxxxxxx "
1!
$end
#10000
b1 +
1'
11
1!
#20000
b0 <
b0 "
0?
0#
0A
0$
0'
01
#30000
b10 +
1'
11
#40000
0'
01
#50000
b11 +
1'
11
#60000
0'
01
#70000
b100 +
1'
11
#80000
0'
01
#90000
b101 +
1'
11
#100000
0'
01
#110000
b110 +
1'
11
#120000
0'
01
#130000
b111 +
1'
11
#140000
0'
01
#150000
b1000 +
1'
11
#160000
0'
01
#170000
b1001 +
1'
11
#180000
0'
01
#190000
b1010 +
1'
11
#200000
0'
01
#210000
b1011 +
0-
05
1'
11
#220000
0'
01
#230000
b11100001000000000 D
0C
b11101000001101101000110000000 M
b11101000010001001001110000000 E
b1100 +
1'
11
#240000
0'
01
#250000
b1101 +
b11101000010001001001110000000 M
b11101000010100101010110000000 E
1'
11
#260000
0'
01
#270000
b11101000010100101010110000000 M
b11101000011000001011110000000 E
b1110 +
1'
11
#280000
0'
01
#290000
b1111 +
b11101000011000001011110000000 M
b11101000011011101100110000000 E
1'
11
#300000
0'
01
#310000
b1 @
b11101000011011101100110000000 M
b11101000011111001101110000000 E
b10000 +
b11101110 )
b11101110 3
1/
1;
1(
12
1'
11
#320000
b11101110 B
b11101110 J
0'
01
#330000
b10001 +
b11101000011111001101110000000 M
b11101000100010101110110000000 E
1'
11
#340000
0'
01
#350000
b11101000100010101110110000000 M
b11101000100110001111110000000 E
b10010 +
1'
11
#360000
0'
01
#370000
b10011 +
b11101000100110001111110000000 M
b11101000101001110000110000000 E
1'
11
#380000
0'
01
#390000
b11101000101001110000110000000 M
b11101000101101010001110000000 E
b10100 +
1'
11
#400000
0'
01
#410000
b1000 @
b10101 +
b0 )
b0 3
b1000 &
b1000 0
b11101000101101010001110000000 M
b11101000110000110010110000000 E
1'
11
#420000
1>
1G
0'
01
#430000
1I
b1011 L
1:
b111011100 N
b11101000110000110010110000000 M
b11101000110100010011110000000 E
b10110 +
1'
11
#440000
1A
1$
0'
01
#450000
b10111 +
b11101000110100010011110000000 M
b11101000110111110100110000000 E
1'
11
#460000
0'
01
#470000
b11101000110111110100110000000 M
b11101000111011010101110000000 E
b11000 +
1'
11
#480000
0'
01
#490000
b11001 +
b11101000111011010101110000000 M
b11101000111110110110110000000 E
1'
11
#500000
0'
01
#510000
b0 @
b11101000111110110110110000000 M
b11101001000010010111110000000 E
b11010 +
0/
0;
0(
02
b1100 &
b1100 0
1'
11
#520000
0>
0G
0'
01
#530000
b11011 +
b11101001000010010111110000000 M
b11101001000101111000110000000 E
1'
11
#540000
0'
01
#550000
b11101001000101111000110000000 M
b11101001001001011001110000000 E
b11100 +
1'
11
#560000
0'
01
#570000
b11101 +
b11101001001001011001110000000 M
b11101001001100111010110000000 E
1'
11
#580000
0'
01
#590000
b11101001001100111010110000000 M
b11101001010000011011110000000 E
b11110 +
1'
11
#600000
0'
01
#610000
b11111 +
b11101001010000011011110000000 M
b11101001010011111100110000000 E
1'
11
#620000
0'
01
#630000
b11101001010011111100110000000 M
b11101001010111011101110000000 E
b100000 +
1'
11
#640000
0'
01
#650000
b100001 +
b11101001010111011101110000000 M
b11101001011010111110110000000 E
1'
11
#660000
0'
01
#670000
b11101001011010111110110000000 M
b11101001011110011111110000000 E
b100010 +
1'
11
#680000
0'
01
#690000
b100011 +
b11101001011110011111110000000 M
b11101001100010000000110000000 E
1'
11
#700000
0'
01
#710000
b11101001100010000000110000000 M
b11101001100101100001110000000 E
b100100 +
1'
11
#720000
0'
01
#730000
b100101 +
b11101001100101100001110000000 M
b11101001101001000010110000000 E
1'
11
#740000
0'
01
#750000
b11101001101001000010110000000 M
b11101001101100100011110000000 E
b100110 +
1'
11
#760000
0'
01
#770000
b100111 +
b11101001101100100011110000000 M
b11101001110000000100110000000 E
1'
11
#780000
0'
01
#790000
b11101001110000000100110000000 M
b11101001110011100101110000000 E
b101000 +
1'
11
#800000
0'
01
#810000
b101001 +
b11101001110011100101110000000 M
b11101001110111000110110000000 E
1'
11
#820000
0'
01
#830000
b11101001110111000110110000000 M
b11101001111010100111110000000 E
b101010 +
1'
11
#840000
0'
01
#850000
b101011 +
b11101001111010100111110000000 M
b11101001111110001000110000000 E
1'
11
#860000
0'
01
#870000
b11101001111110001000110000000 M
b11101010000001101001110000000 E
b101100 +
1'
11
#880000
0'
01
#890000
b101101 +
b11101010000001101001110000000 M
b11101010000101001010110000000 E
1'
11
#900000
0'
01
#910000
b11101010000101001010110000000 M
b11101010001000101011110000000 E
b101110 +
1'
11
#920000
0'
01
#930000
b101111 +
b11101010001000101011110000000 M
b11101010001100001100110000000 E
1'
11
#940000
0'
01
#950000
b11101010001100001100110000000 M
b11101010001111101101110000000 E
b110000 +
1'
11
#960000
0'
01
#970000
b110001 +
b11101010001111101101110000000 M
b11101010010011001110110000000 E
1'
11
#980000
0'
01
#990000
b11101010010011001110110000000 M
b11101010010110101111110000000 E
b110010 +
1'
11
#1000000
0'
01
#1010000
b110011 +
b11101010010110101111110000000 M
b11101010011010010000110000000 E
1'
11
#1020000
0'
01
#1030000
b11101010011010010000110000000 M
b11101010011101110001110000000 E
b110100 +
1'
11
#1040000
0'
01
#1050000
b110101 +
b11101010011101110001110000000 M
b11101010100001010010110000000 E
1'
11
#1060000
0'
01
#1070000
b11101010100001010010110000000 M
b11101010100100110011110000000 E
b110110 +
1'
11
#1080000
0'
01
#1090000
b110111 +
b11101010100100110011110000000 M
b11101010101000010100110000000 E
1'
11
#1100000
0'
01
#1110000
b11101010101000010100110000000 M
b11101010101011110101110000000 E
b111000 +
1'
11
#1120000
0'
01
#1130000
b111001 +
b11101010101011110101110000000 M
b11101010101111010110110000000 E
1'
11
#1140000
0'
01
#1150000
b11101010101111010110110000000 M
b11101010110010110111110000000 E
b111010 +
1'
11
#1160000
0'
01
#1170000
b111011 +
b11101010110010110111110000000 M
b11101010110110011000110000000 E
1'
11
#1180000
0'
01
#1190000
b11101010110110011000110000000 M
b11101010111001111001110000000 E
b111100 +
1'
11
#1200000
0'
01
#1210000
b111101 +
b11101010111001111001110000000 M
b11101010111101011010110000000 E
1'
11
#1220000
0'
01
#1230000
b11101010111101011010110000000 M
b11101011000000111011110000000 E
b111110 +
1'
11
#1240000
0'
01
#1250000
b111111 +
b11101011000000111011110000000 M
b11101011000100011100110000000 E
1'
11
#1260000
0'
01
#1270000
b11101011000100011100110000000 M
b11101011000111111101110000000 E
b1000000 +
1'
11
#1280000
0'
01
#1290000
b1000001 +
b11101011000111111101110000000 M
b11101011001011011110110000000 E
1'
11
#1300000
0'
01
#1310000
b11101011001011011110110000000 M
b11101011001110111111110000000 E
b1000010 +
1'
11
#1320000
0'
01
#1330000
b1000011 +
b11101011001110111111110000000 M
b11101011010010100000110000000 E
1'
11
#1340000
0'
01
#1350000
b11101011010010100000110000000 M
b11101011010110000001110000000 E
b1000100 +
1'
11
#1360000
0'
01
#1370000
b1000101 +
b11101011010110000001110000000 M
b11101011011001100010110000000 E
1'
11
#1380000
0'
01
#1390000
b11101011011001100010110000000 M
b11101011011101000011110000000 E
b1000110 +
1'
11
#1400000
0'
01
#1410000
b1000111 +
b11101011011101000011110000000 M
b11101011100000100100110000000 E
1'
11
#1420000
0'
01
#1430000
b11101011100000100100110000000 M
b11101011100100000101110000000 E
b1001000 +
1'
11
#1440000
0'
01
#1450000
b1001001 +
b11101011100100000101110000000 M
b11101011100111100110110000000 E
1'
11
#1460000
0'
01
#1470000
b11101011100111100110110000000 M
b11101011101011000111110000000 E
b1001010 +
1'
11
#1480000
0'
01
#1490000
b1001011 +
b11101011101011000111110000000 M
b11101011101110101000110000000 E
1'
11
#1500000
0'
01
#1510000
b11101011101110101000110000000 M
b11101011110010001001110000000 E
b1001100 +
1'
11
#1520000
0'
01
#1530000
b1001101 +
b11101011110010001001110000000 M
b11101011110101101010110000000 E
1'
11
#1540000
0'
01
#1550000
b11101011110101101010110000000 M
b11101011111001001011110000000 E
b1001110 +
1'
11
#1560000
0'
01
#1570000
b1001111 +
b11101011111001001011110000000 M
b11101011111100101100110000000 E
1'
11
#1580000
0'
01
#1590000
b11101011111100101100110000000 M
b11101100000000001101110000000 E
b1010000 +
1'
11
#1600000
0'
01
#1610000
b1010001 +
b11101100000000001101110000000 M
b11101100000011101110110000000 E
1'
11
#1620000
0'
01
#1630000
b11101100000011101110110000000 M
b11101100000111001111110000000 E
b1010010 +
1'
11
#1640000
0'
01
#1650000
b1010011 +
b11101100000111001111110000000 M
b11101100001010110000110000000 E
1'
11
#1660000
0'
01
#1670000
b11101100001010110000110000000 M
b11101100001110010001110000000 E
b1010100 +
1'
11
#1680000
0'
01
#1690000
b1010101 +
b11101100001110010001110000000 M
b11101100010001110010110000000 E
1'
11
#1700000
0'
01
#1710000
b11101100010001110010110000000 M
b11101100010101010011110000000 E
b1010110 +
1'
11
#1720000
0'
01
#1730000
b1010111 +
b11101100010101010011110000000 M
b11101100011000110100110000000 E
1'
11
#1740000
0'
01
#1750000
b11101100011000110100110000000 M
b11101100011100010101110000000 E
b1011000 +
1'
11
#1760000
0'
01
#1770000
b1011001 +
b11101100011100010101110000000 M
b11101100011111110110110000000 E
1'
11
#1780000
0'
01
#1790000
b11101100011111110110110000000 M
b11101100100011010111110000000 E
b1011010 +
1'
11
#1800000
0'
01
#1810000
b1011011 +
b11101100100011010111110000000 M
b11101100100110111000110000000 E
1'
11
#1820000
0'
01
#1830000
b11101100100110111000110000000 M
b11101100101010011001110000000 E
b1011100 +
1'
11
#1840000
0'
01
#1850000
b1011101 +
b11101100101010011001110000000 M
b11101100101101111010110000000 E
1'
11
#1860000
0'
01
#1870000
b11101100101101111010110000000 M
b11101100110001011011110000000 E
b1011110 +
1'
11
#1880000
0'
01
#1890000
b1011111 +
b11101100110001011011110000000 M
b11101100110100111100110000000 E
1'
11
#1900000
0'
01
#1910000
b11101100110100111100110000000 M
b11101100111000011101110000000 E
b1100000 +
1'
11
#1920000
0'
01
#1930000
b1100001 +
b11101100111000011101110000000 M
b11101100111011111110110000000 E
1'
11
#1940000
0'
01
#1950000
b11101100111011111110110000000 M
b11101100111111011111110000000 E
b1100010 +
1'
11
#1960000
0'
01
#1970000
b1100011 +
b11101100111111011111110000000 M
b11101101000011000000110000000 E
1'
11
#1980000
0'
01
#1990000
b11101101000011000000110000000 M
b11101101000110100001110000000 E
b1100100 +
1'
11
#2000000
0'
01
#2010000
b1100101 +
b11101101000110100001110000000 M
b11101101001010000010110000000 E
1'
11
#2020000
0'
01
#2030000
b11101101001010000010110000000 M
b11101101001101100011110000000 E
b1100110 +
1'
11
#2040000
0'
01
#2050000
b1100111 +
b11101101001101100011110000000 M
b11101101010001000100110000000 E
1'
11
#2060000
0'
01
#2070000
b11101101010001000100110000000 M
b11101101010100100101110000000 E
b1101000 +
1'
11
#2080000
0'
01
#2090000
b1101001 +
b11101101010100100101110000000 M
b11101101011000000110110000000 E
1'
11
#2100000
0'
01
#2110000
b11101101011000000110110000000 M
b11101101011011100111110000000 E
b1101010 +
1'
11
#2120000
0'
01
#2130000
b1101011 +
b11101101011011100111110000000 M
b11101101011111001000110000000 E
1'
11
#2140000
0'
01
#2150000
b11101101011111001000110000000 M
b11101101100010101001110000000 E
b1101100 +
1'
11
#2160000
0'
01
#2170000
b1101101 +
b11101101100010101001110000000 M
b11101101100110001010110000000 E
1'
11
#2180000
0'
01
#2190000
b11101101100110001010110000000 M
b11101101101001101011110000000 E
b1101110 +
1'
11
#2200000
0'
01
#2210000
b1101111 +
b11101101101001101011110000000 M
b11101101101101001100110000000 E
1'
11
#2220000
0'
01
#2230000
b11101101101101001100110000000 M
b11101101110000101101110000000 E
b1110000 +
1'
11
#2240000
0'
01
#2250000
b1110001 +
b11101101110000101101110000000 M
b11101101110100001110110000000 E
1'
11
#2260000
0'
01
#2270000
b11101101110100001110110000000 M
b11101101110111101111110000000 E
b1110010 +
1'
11
#2280000
0'
01
#2290000
b1110011 +
b11101101110111101111110000000 M
b11101101111011010000110000000 E
1'
11
#2300000
0'
01
#2310000
b11101101111011010000110000000 M
b11101101111110110001110000000 E
b1110100 +
1'
11
#2320000
0'
01
#2330000
b1110101 +
b11101101111110110001110000000 M
b11101110000010010010110000000 E
1'
11
#2340000
0'
01
#2350000
b11101110000010010010110000000 M
b11101110000101110011110000000 E
b1110110 +
1'
11
#2360000
0'
01
#2370000
b1110111 +
b11101110000101110011110000000 M
b11101110001001010100110000000 E
1'
11
#2380000
0'
01
#2390000
b11101110001001010100110000000 M
b11101110001100110101110000000 E
b1111000 +
1'
11
#2400000
0'
01
#2410000
b1111001 +
b11101110001100110101110000000 M
b11101110010000010110110000000 E
1'
11
#2420000
0'
01
#2430000
b11101110010000010110110000000 M
b11101110010011110111110000000 E
b1111010 +
1'
11
#2440000
0'
01
#2450000
b1111011 +
b11101110010011110111110000000 M
b11101110010111011000110000000 E
1'
11
#2460000
0'
01
#2470000
b11101110010111011000110000000 M
b11101110011010111001110000000 E
b1111100 +
1'
11
#2480000
0'
01
#2490000
b1111101 +
b11101110011010111001110000000 M
b11101110011110011010110000000 E
1'
11
#2500000
0'
01
#2510000
b11101110011110011010110000000 M
b11101110100001111011110000000 E
b1111110 +
1'
11
#2520000
0'
01
#2530000
b1111111 +
b11101110100001111011110000000 M
b11101110100101011100110000000 E
1'
11
#2540000
0'
01
#2550000
b11101110100101011100110000000 M
b11101110101000111101110000000 E
b10000000 +
1'
11
#2560000
0'
01
#2570000
b10000001 +
b11101110101000111101110000000 M
b11101110101100011110110000000 E
1'
11
#2580000
0'
01
#2590000
b11101110101100011110110000000 M
b11101110101111111111110000000 E
b10000010 +
1'
11
#2600000
0'
01
#2610000
b10000011 +
b11101110101111111111110000000 M
b11101110110011100000110000000 E
1'
11
#2620000
0'
01
#2630000
b11101110110011100000110000000 M
b11101110110111000001110000000 E
b10000100 +
1'
11
#2640000
0'
01
#2650000
b10000101 +
b11101110110111000001110000000 M
b11101110111010100010110000000 E
1'
11
#2660000
0'
01
#2670000
b11101110111010100010110000000 M
b11101110111110000011110000000 E
b10000110 +
1'
11
#2680000
0'
01
#2690000
b10000111 +
b11101110111110000011110000000 M
b11101111000001100100110000000 E
1'
11
#2700000
0'
01
#2710000
b11101111000001100100110000000 M
b11101111000101000101110000000 E
b10001000 +
1'
11
#2720000
0'
01
#2730000
b10001001 +
b11101111000101000101110000000 M
b11101111001000100110110000000 E
1'
11
#2740000
0'
01
#2750000
b11101111001000100110110000000 M
b11101111001100000111110000000 E
b10001010 +
1'
11
#2760000
0'
01
#2770000
b10001011 +
b11101111001100000111110000000 M
b11101111001111101000110000000 E
1'
11
#2780000
0'
01
#2790000
b11101111001111101000110000000 M
b11101111010011001001110000000 E
b10001100 +
1'
11
#2800000
0'
01
#2810000
b10001101 +
b11101111010011001001110000000 M
b11101111010110101010110000000 E
1'
11
#2820000
0'
01
#2830000
b11101111010110101010110000000 M
b11101111011010001011110000000 E
b10001110 +
1'
11
#2840000
0'
01
#2850000
b10001111 +
b11101111011010001011110000000 M
b11101111011101101100110000000 E
1'
11
#2860000
0'
01
#2870000
b11101111011101101100110000000 M
b11101111100001001101110000000 E
b10010000 +
1'
11
#2880000
0'
01
#2890000
b10010001 +
b11101111100001001101110000000 M
b11101111100100101110110000000 E
1'
11
#2900000
0'
01
#2910000
b11101111100100101110110000000 M
b11101111101000001111110000000 E
b10010010 +
1'
11
#2920000
0'
01
#2930000
b10010011 +
b11101111101000001111110000000 M
b11101111101011110000110000000 E
1'
11
#2940000
0'
01
#2950000
b11101111101011110000110000000 M
b11101111101111010001110000000 E
b10010100 +
1'
11
#2960000
0'
01
#2970000
b10010101 +
b11101111101111010001110000000 M
b11101111110010110010110000000 E
1'
11
#2980000
0'
01
#2990000
b11101111110010110010110000000 M
b11101111110110010011110000000 E
b10010110 +
1'
11
#3000000
0'
01
#3010000
b10010111 +
b11101111110110010011110000000 M
b11101111111001110100110000000 E
1'
11
#3020000
0'
01
#3030000
b11101111111001110100110000000 M
b11101111111101010101110000000 E
b10011000 +
1'
11
#3040000
0'
01
#3050000
b10011001 +
b11101111111101010101110000000 M
b11110000000000110110110000000 E
1'
11
#3060000
0'
01
#3070000
b11110000000000110110110000000 M
b11110000000100010111110000000 E
b10011010 +
1'
11
#3080000
0'
01
#3090000
b10011011 +
b11110000000100010111110000000 M
b11110000000111111000110000000 E
1'
11
#3100000
0'
01
#3110000
b11110000000111111000110000000 M
b11110000001011011001110000000 E
b10011100 +
1'
11
#3120000
0'
01
#3130000
b10011101 +
b11110000001011011001110000000 M
b11110000001110111010110000000 E
1'
11
#3140000
0'
01
#3150000
b11110000001110111010110000000 M
b11110000010010011011110000000 E
b10011110 +
1'
11
#3160000
0'
01
#3170000
b10011111 +
b11110000010010011011110000000 M
b11110000010101111100110000000 E
1'
11
#3180000
0'
01
#3190000
b11110000010101111100110000000 M
b11110000011001011101110000000 E
b10100000 +
1'
11
#3200000
0'
01
#3210000
b10100001 +
b11110000011001011101110000000 M
b11110000011100111110110000000 E
1'
11
#3220000
0'
01
#3230000
b11110000011100111110110000000 M
b11110000100000011111110000000 E
b10100010 +
1'
11
#3240000
0'
01
#3250000
b10100011 +
b11110000100000011111110000000 M
b11110000100100000000110000000 E
1'
11
#3260000
0'
01
#3270000
b11110000100100000000110000000 M
b11110000100111100001110000000 E
b10100100 +
1'
11
#3280000
0'
01
#3290000
b10100101 +
b11110000100111100001110000000 M
b11110000101011000010110000000 E
1'
11
#3300000
0'
01
#3310000
b11110000101011000010110000000 M
b11110000101110100011110000000 E
b10100110 +
1'
11
#3320000
0'
01
#3330000
b10100111 +
b11110000101110100011110000000 M
b11110000110010000100110000000 E
1'
11
#3340000
0'
01
#3350000
b11110000110010000100110000000 M
b11110000110101100101110000000 E
b10101000 +
1'
11
#3360000
0'
01
#3370000
b10101001 +
b11110000110101100101110000000 M
b11110000111001000110110000000 E
1'
11
#3380000
0'
01
#3390000
b11110000111001000110110000000 M
b11110000111100100111110000000 E
b10101010 +
1'
11
#3400000
0'
01
#3410000
b10101011 +
b11110000111100100111110000000 M
b11110001000000001000110000000 E
1'
11
#3420000
0'
01
#3430000
b11110001000000001000110000000 M
b11110001000011101001110000000 E
b10101100 +
1'
11
#3440000
0'
01
#3450000
b10101101 +
b11110001000011101001110000000 M
b11110001000111001010110000000 E
1'
11
#3460000
0'
01
#3470000
b11110001000111001010110000000 M
b11110001001010101011110000000 E
b10101110 +
1'
11
#3480000
0'
01
#3490000
b10101111 +
b11110001001010101011110000000 M
b11110001001110001100110000000 E
1'
11
#3500000
0'
01
#3510000
b11110001001110001100110000000 M
b11110001010001101101110000000 E
b10110000 +
1'
11
#3520000
0'
01
#3530000
b10110001 +
b11110001010001101101110000000 M
b11110001010101001110110000000 E
1'
11
#3540000
0'
01
#3550000
b11110001010101001110110000000 M
b11110001011000101111110000000 E
b10110010 +
1'
11
#3560000
0'
01
