hdl/uart/uart.v
module uart(
	// Outputs
	uart_busy,   // High means UART is transmitting
	uart_tx,     // UART transmit wire
	
	uart_dat_o, //RX
	uart_rx_busy, //RX
	done, //RX
	
	// Inputs
	uart_wr_i,   // Raise to transmit byte
	
	uart_rd_i,	//RX
	uart_rx, //RX
	
	uart_dat_i,  // 8-bit data
	sys_clk_i,   // System clock, 50MHz
	sys_rst_i    // System reset
);

	input uart_wr_i;
	input [7:0]uart_dat_i;
	input sys_clk_i;
	input sys_rst_i;

	//----------------RX
	input uart_rd_i;
	input uart_rx;
	
	output reg [7:0]uart_dat_o;
	
	output uart_rx_busy;
	
	reg [3:0] bitcount_rx;
	
	wire receiving = (bitcount_rx > 0 & bitcount_rx < 12) ? 1 : 0;
	wire uart_rx_busy = (bitcount_rx > 0 & bitcount_rx < 10) ? 1 : 0;
	
	reg [7:0]uart_dat;
	output reg done;
	//----------------RX
	 
	output uart_busy;
	output uart_tx;

	reg [3:0] bitcount;
	reg [8:0] shifter;
	reg uart_tx;

	wire uart_busy = |bitcount[3:1];
	wire sending = |bitcount;

	// sys_clk_i is 50MHz.  We want a 115200Hz clock

	reg [28:0] d;
	wire [28:0] dInc = d[28] ? (115200) : (115200 - 50000000);
	wire [28:0] dNxt = d + dInc;
	wire ser_clk = ~d[28];
  
	always @(posedge sys_clk_i)
		if (sys_rst_i) begin
			d = 0;
		end else begin
			d = dNxt;
		end

	always @(posedge sys_clk_i) begin
		if (sys_rst_i) begin
			uart_tx <= 1;
			bitcount <= 0;
			shifter <= 0;
			
			done <= 0;
			uart_dat <= 0;
			uart_dat_o <= 0;
			bitcount_rx = 0;
		end else begin
		// just got a new byte
			if (uart_wr_i & ~uart_busy) begin
				shifter <= { uart_dat_i[7:0], 1'h0 };
				bitcount <= (1 + 8 + 2);
			end

			if (sending & ser_clk) begin
				{ shifter, uart_tx } <= { 1'h1 , shifter };
				bitcount <= bitcount - 1;
			end
			
			// UART RX
			if(uart_rd_i & ~uart_busy & ~uart_rx_busy & ~uart_rx & ~receiving) begin
				bitcount_rx = 1;
				done <= 0;
				uart_dat <= 0;
				uart_dat_o <= 0;
			end
			
			if(done)
				uart_dat_o <= uart_dat_o;
				
			
			if(~done & receiving & ser_clk) begin
				uart_dat <= {uart_dat, uart_rx};
				bitcount_rx = bitcount_rx + 1;
				done <= 0;
			end
			
			if(~uart_rx_busy & receiving) begin
				done <= 1;
				uart_dat_o <= uart_dat;
			end
			
			if(~uart_rx_busy & receiving & ser_clk) begin
				bitcount_rx = 12;
				done <= 0;
			end
				
		end
	end
  
endmodule

hdl/uart/peripheral_uart.v
module peripheral_uart(
	clk,
	rst,
	d_in,
	
	cs,
	addr,
	rd,
	wr,
	d_out,
	uart_tx,
	
	uart_rx,
	//done,
	
	ledout 
	
	);
  
	input clk;
	input rst;
	input [15:0]d_in;
	input cs;
	input [3:0]addr; // 4 LSB from j1_io_addr
	input rd;
	input wr;
	
	//-----------------rx
	input uart_rx;
	wire [7:0]uart_dat_o;
	wire uart_rx_busy;
	wire done;
	//-----------------rx
	
	output reg [15:0]d_out;
	output uart_tx;
	output reg ledout = 0;

	//---------------------------------- regs and wires-------------------------------

	reg [3:0] sel_mux; 	//selector mux_4  and demux_4
	reg [7:0] d_in_uart; // data in uart
	wire uart_busy;  // out_uart

	//------------------------------------ regs and wires-------------------------------

	//----address_decoder------------------
	always @(*) begin
		case (addr)
			4'h0:begin sel_mux = (cs && rd) ? 4'b0001 : 4'b0000; end //busy
			4'h2:begin sel_mux = (cs && rd) ? 4'b0010 : 4'b0000; end //rx
			4'h4:begin sel_mux = (cs && rd) ? 4'b0100 : 4'b0000; end //done
			4'h6:begin sel_mux = (cs && wr) ? 4'b1000 : 4'b0000; end //data_in!!!
			4'h8:begin sel_mux = (cs && wr) ? 4'b1010 : 4'b0000; end //ledout
			default:begin sel_mux = 4'b0000; end
		endcase
	end
	//-----------------address_decoder--------------------

	//-------------------- escritura de registros
	always @(negedge clk) begin
		d_in_uart = (sel_mux[3]) ? d_in[7:0] : d_in_uart; // data in uart
		// ledout = (sel_mux[2]) ? d_in[0] : ledout; 	// write ledout register 
		ledout = uart_busy | uart_rx_busy; // NO IBA
	end
	//-------------------- escritura de registros

	//-----------------------mux_4 : multiplexa salidas del periferico
	always @(negedge clk) begin
		case (sel_mux)
			4'b0001: d_out[0] = uart_busy | uart_rx_busy;	// data out uart
			4'b0010: d_out = uart_dat_o[7:0]; //rx dato
			4'b0100: d_out[0] = done; //rx done
			default: d_out = 0;
		endcase
	end
	//----------------------------------------------mux_4

										//(addr != 4'h4): se hace para evitar escrituras fantasma
	uart uart(.uart_busy(uart_busy), .uart_tx(uart_tx), .uart_dat_o(uart_dat_o), .uart_rx_busy(uart_rx_busy), .done(done), .uart_wr_i(cs && wr && (addr != 4'h8) ), .uart_rd_i(cs && rd && (addr != 4'h8)), .uart_rx(uart_rx) , .uart_dat_i(d_in_uart), .sys_clk_i(clk), .sys_rst_i(rst));// System clock, 


endmodule

hdl/uart/peripheral_uart_TB.v
`timescale 1ns / 1ps

`define SIMULATION

module peripheral_uart_TB;

	reg clk;
	reg rst;
	reg [15:0]d_in;
	reg cs;
	reg [3:0]addr; // 4 LSB from j1_io_addr
	reg rd;
	reg wr;
	
	//--------rx
	reg uart_rx;
	wire done;
	//--------rx
	
	wire [15:0]d_out;
	wire uart_tx;
	wire ledout = 0;
	
	parameter PERIOD = 20;
	parameter real DUTY_CYCLE = 0.5;
	parameter OFFSET = 0;
	
	reg [20:0] i;
	reg [10:0] fac;
	reg [20:0] fac2;
	reg [7:0] flag;
	
	event reset_trigger;
		
	peripheral_uart p_uart(.clk(clk) , .rst(rst) , .d_in(d_in) , .cs(cs) , .addr(addr) , .rd(rd) , .wr(wr) , .d_out(d_out) ,  .uart_tx(uart_tx) , .uart_rx(uart_rx) , .done(done) , .ledout(ledout) );
	
	initial begin// Initialize Inputs
		flag = 0;
		fac = 4000;
		fac2 = 10000;
		
		clk = 1;
		rst = 1;
		d_in = 0;
		cs = 0;
		addr = 3'b000;
		rd = 0;
		wr = 0;
		
		uart_rx=1;
	end

	initial begin// Process for sys_clk_i
		#OFFSET;
		forever begin
			clk = 1'b0;
			#(PERIOD-(PERIOD*DUTY_CYCLE)) clk = 1'b1;
			#(PERIOD*DUTY_CYCLE);
		end
	end
	
	initial begin
		@ (posedge clk)
		@ (posedge clk)
		rst = 0;
				
		for(i = 0; i < 30000; i = i+1) begin
			@ (posedge clk);
			
			if(i == 20) begin
				addr = 4'b0110;
				cs = 1;
				wr = 1;
				rd = 0;
				d_in = 8'h26;
				uart_rx=1;
			end
			
			if(i == 30) begin
				addr = 4'b0110;
				cs = 1;
				wr = 1;
				rd = 0;
				d_in = 8'h0;
			end
			
			if(i == 40) begin
				addr = 4'b0000;
				cs = 0;
				wr = 0;
				rd = 0;
			end
			
//			envio 2
			
			if(i == 7000) begin
				addr = 4'b0110;
				cs = 1;
				wr = 1;
				rd = 0;
				d_in = 8'h2D;
			end
			
			if(i == 7005) begin
				addr = 4'b0110;
				cs = 1;
				wr = 1;
				rd = 0;
				d_in = 8'h0;
			end
			
			if(i == 7010) begin
				addr = 4'b0000;
				cs = 0;
				wr = 0;
				rd = 0;
			end
			
			if(i == 12153) begin
				addr = 4'h2;
				cs = 1;
				wr = 0;
				rd = 1;
			end
			
			
			//--------------------RX 10101110 -170
			
			if(i == 11150+fac) begin
				 // inicio de recepción
			end
			
			if(i == 11520+fac) begin
				uart_rx = 0; // inicio de recepción
			end
			
			if(i == 11954+fac) begin
				uart_rx = 1;
			end
			
			if(i == 12388+fac) begin
				uart_rx = 0;
			end
			
			if(i == 12822+fac) begin
				uart_rx = 1;
			end
			
			if(i == 13256+fac) begin
				uart_rx = 0;
			end
			
			if(i == 13690+fac) begin
				uart_rx = 1;
			end
			
			if(i == 14124+fac) begin
				uart_rx = 1;
			end
			
			if(i == 14558+fac) begin
				uart_rx = 1;
			end
			
			if(i == 14992+fac) begin
				uart_rx = 0;
			end
			// end
			if(i == 15426+fac) begin
				uart_rx = 1;
			end
			//--------------------RX  10101110-170
			
			if(i == 19900) begin
				addr = 4'h2;
				cs = 1;
				wr = 0;
				rd = 1;
			end
			
			//--------------------RX 00000011 -3
			
			if(i == 11520+fac2) begin
				uart_rx = 0; // inicio de recepción
				flag = 1;
			end
			
			if(i == 11954+fac2) begin
				uart_rx = 0;
				flag = 2;
			end
			
			if(i == 12388+fac2) begin
				uart_rx = 0;
			end
			
			if(i == 12822+fac2) begin
				uart_rx = 0;
			end
			
			if(i == 13256+fac2) begin
				uart_rx = 0;
			end
			
			if(i == 13690+fac2) begin
				uart_rx = 0;
			end
			
			if(i == 14124+fac2) begin
				uart_rx = 0;
			end
			
			if(i == 14558+fac2) begin
				uart_rx = 1;
			end
			
			if(i == 14992+fac2) begin
				uart_rx = 1;
			end
			// end
			if(i == 15426+fac2) begin
				uart_rx = 1;
			end
			//--------------------RX 00000011 -3

		end
	end
	
	initial begin: TEST_CASE
	  	$dumpfile("peripheral_uart_TB.vcd");
	  	$dumpvars(-1, peripheral_uart_TB);
	
	  	#10 -> reset_trigger;
	  	#((PERIOD*DUTY_CYCLE)*60000) $finish;
	end

endmodule

hdl/uart/simulation/peripheral_uart_TB.vcd
$date
	Mon Jun 15 11:10:55 2015
$end
$version
	Icarus Verilog
$end
$timescale
	1ps
$end
$scope module peripheral_uart_TB $end
$var event 1 ! reset_trigger $end
$var wire 16 " d_out [15:0] $end
$var wire 1 # done $end
$var wire 1 $ ledout $end
$var wire 1 % uart_tx $end
$var reg 4 & addr [3:0] $end
$var reg 1 ' clk $end
$var reg 1 ( cs $end
$var reg 16 ) d_in [15:0] $end
$var reg 11 * fac [10:0] $end
$var reg 21 + fac2 [20:0] $end
$var reg 8 , flag [7:0] $end
$var reg 21 - i [20:0] $end
$var reg 1 . rd $end
$var reg 1 / rst $end
$var reg 1 0 uart_rx $end
$var reg 1 1 wr $end
$scope module p_uart $end
$var wire 4 2 addr [3:0] $end
$var wire 1 3 clk $end
$var wire 1 4 cs $end
$var wire 16 5 d_in [15:0] $end
$var wire 1 # done $end
$var wire 1 6 rd $end
$var wire 1 7 rst $end
$var wire 1 8 uart_busy $end
$var wire 8 9 uart_dat_o [7:0] $end
$var wire 1 : uart_rx $end
$var wire 1 ; uart_rx_busy $end
$var wire 1 % uart_tx $end
$var wire 1 < wr $end
$var reg 8 = d_in_uart [7:0] $end
$var reg 16 > d_out [15:0] $end
$var reg 1 ? ledout $end
$var reg 4 @ sel_mux [3:0] $end
$scope module uart $end
$var wire 29 A dInc [28:0] $end
$var wire 29 B dNxt [28:0] $end
$var wire 1 C receiving $end
$var wire 1 D sending $end
$var wire 1 E ser_clk $end
$var wire 1 3 sys_clk_i $end
$var wire 1 7 sys_rst_i $end
$var wire 1 8 uart_busy $end
$var wire 8 F uart_dat_i [7:0] $end
$var wire 1 G uart_rd_i $end
$var wire 1 : uart_rx $end
$var wire 1 ; uart_rx_busy $end
$var wire 1 H uart_wr_i $end
$var reg 4 I bitcount [3:0] $end
$var reg 4 J bitcount_rx [3:0] $end
$var reg 29 K d [28:0] $end
$var reg 1 L done $end
$var reg 9 M shifter [8:0] $end
$var reg 8 N uart_dat [7:0] $end
$var reg 8 O uart_dat_o [7:0] $end
$var reg 1 P uart_tx $end
$upscope $end
$upscope $end
$scope begin TEST_CASE $end
$upscope $end
$upscope $end
$enddefinitions $end
#0
$dumpvars
1P
b0 O
b0 N
b0 M
0L
b0 K
b0 J
b0 I
0H
0G
bx F
1E
0D
0C
b11101000001101101000110000000 B
b11101000001101101000110000000 A
b0 @
x?
b0 >
bx =
0<
0;
1:
b0 9
08
17
06
b0 5
04
03
b0 2
01
10
1/
0.
bx -
b0 ,
b10011100010000 +
b11110100000 *
b0 )
0(
0'
b0 &
1%
x$
0#
b0 "
1!
$end
#10000
1'
13
1!
#20000
0?
0$
0'
03
#30000
b11100001000000000 A
0E
b11101000001101101000110000000 K
b11101000010001001001110000000 B
b0 -
0/
07
1'
13
#40000
0'
03
#50000
b1 -
b11101000010001001001110000000 K
b11101000010100101010110000000 B
1'
13
#60000
0'
03
#70000
b11101000010100101010110000000 K
b11101000011000001011110000000 B
b10 -
1'
13
#80000
0'
03
#90000
b11 -
b11101000011000001011110000000 K
b11101000011011101100110000000 B
1'
13
#100000
0'
03
#110000
b11101000011011101100110000000 K
b11101000011111001101110000000 B
b100 -
1'
13
#120000
0'
03
#130000
b101 -
b11101000011111001101110000000 K
b11101000100010101110110000000 B
1'
13
#140000
0'
03
#150000
b11101000100010101110110000000 K
b11101000100110001111110000000 B
b110 -
1'
13
#160000
0'
03
#170000
b111 -
b11101000100110001111110000000 K
b11101000101001110000110000000 B
1'
13
#180000
0'
03
#190000
b11101000101001110000110000000 K
b11101000101101010001110000000 B
b1000 -
1'
13
#200000
0'
03
#210000
b1001 -
b11101000101101010001110000000 K
b11101000110000110010110000000 B
1'
13
#220000
0'
03
#230000
b11101000110000110010110000000 K
b11101000110100010011110000000 B
b1010 -
1'
13
#240000
0'
03
#250000
b1011 -
b11101000110100010011110000000 K
b11101000110111110100110000000 B
1'
13
#260000
0'
03
#270000
b11101000110111110100110000000 K
b11101000111011010101110000000 B
b1100 -
1'
13
#280000
0'
03
#290000
b1101 -
b11101000111011010101110000000 K
b11101000111110110110110000000 B
1'
13
#300000
0'
03
#310000
b11101000111110110110110000000 K
b11101001000010010111110000000 B
b1110 -
1'
13
#320000
0'
03
#330000
b1111 -
b11101001000010010111110000000 K
b11101001000101111000110000000 B
1'
13
#340000
0'
03
#350000
b11101001000101111000110000000 K
b11101001001001011001110000000 B
b10000 -
1'
13
#360000
0'
03
#370000
b10001 -
b11101001001001011001110000000 K
b11101001001100111010110000000 B
1'
13
#380000
0'
03
#390000
b11101001001100111010110000000 K
b11101001010000011011110000000 B
b10010 -
1'
13
#400000
0'
03
#410000
b10011 -
b11101001010000011011110000000 K
b11101001010011111100110000000 B
1'
13
#420000
0'
03
#430000
b11101001010011111100110000000 K
b11101001010111011101110000000 B
b10100 -
1'
13
#440000
0'
03
#450000
1H
b1000 @
b10101 -
b100110 )
b100110 5
11
1<
1(
14
b110 &
b110 2
b11101001010111011101110000000 K
b11101001011010111110110000000 B
1'
13
#460000
b100110 =
b100110 F
0'
03
#470000
18
b1011 I
1D
b1001100 M
b11101001011010111110110000000 K
b11101001011110011111110000000 B
b10110 -
1'
13
#480000
1?
x$
0'
03
#490000
b10111 -
b11101001011110011111110000000 K
b11101001100010000000110000000 B
1'
13
#500000
0'
03
#510000
b11101001100010000000110000000 K
b11101001100101100001110000000 B
b11000 -
1'
13
#520000
0'
03
#530000
b11001 -
b11101001100101100001110000000 K
b11101001101001000010110000000 B
1'
13
#540000
0'
03
#550000
b11101001101001000010110000000 K
b11101001101100100011110000000 B
b11010 -
1'
13
#560000
0'
03
#570000
b11011 -
b11101001101100100011110000000 K
b11101001110000000100110000000 B
1'
13
#580000
0'
03
#590000
b11101001110000000100110000000 K
b11101001110011100101110000000 B
b11100 -
1'
13
#600000
0'
03
#610000
b11101 -
b11101001110011100101110000000 K
b11101001110111000110110000000 B
1'
13
#620000
0'
03
#630000
b11101001110111000110110000000 K
b11101001111010100111110000000 B
b11110 -
1'
13
#640000
0'
03
#650000
b11111 -
b0 )
b0 5
b11101001111010100111110000000 K
b11101001111110001000110000000 B
1'
13
#660000
b0 =
b0 F
0'
03
#670000
b11101001111110001000110000000 K
b11101010000001101001110000000 B
b100000 -
1'
13
#680000
0'
03
#690000
b100001 -
b11101010000001101001110000000 K
b11101010000101001010110000000 B
1'
13
#700000
0'
03
#710000
b11101010000101001010110000000 K
b11101010001000101011110000000 B
b100010 -
1'
13
#720000
0'
03
#730000
b100011 -
b11101010001000101011110000000 K
b11101010001100001100110000000 B
1'
13
#740000
0'
03
#750000
b11101010001100001100110000000 K
b11101010001111101101110000000 B
b100100 -
1'
13
#760000
0'
03
#770000
b100101 -
b11101010001111101101110000000 K
b11101010010011001110110000000 B
1'
13
#780000
0'
03
#790000
b11101010010011001110110000000 K
b11101010010110101111110000000 B
b100110 -
1'
13
#800000
0'
03
#810000
b100111 -
b11101010010110101111110000000 K
b11101010011010010000110000000 B
1'
13
#820000
0'
03
#830000
b11101010011010010000110000000 K
b11101010011101110001110000000 B
b101000 -
1'
13
#840000
0'
03
#850000
0H
b0 @
b101001 -
01
0<
0(
04
b0 &
b0 2
b11101010011101110001110000000 K
b11101010100001010010110000000 B
1'
13
#860000
0'
03
#870000
b11101010100001010010110000000 K
b11101010100100110011110000000 B
b101010 -
1'
13
#880000
0'
03
#890000
b101011 -
b11101010100100110011110000000 K
b11101010101000010100110000000 B
1'
13
#900000
0'
03
#910000
b11101010101000010100110000000 K
b11101010101011110101110000000 B
b101100 -
1'
13
#920000
0'
03
#930000
b101101 -
b11101010101011110101110000000 K
b11101010101111010110110000000 B
1'
13
#940000
0'
03
#950000
b11101010101111010110110000000 K
b11101010110010110111110000000 B
b101110 -
1'
13
#960000
0'
03
#970000
b101111 -
b11101010110010110111110000000 K
b11101010110110011000110000000 B
1'
13
#980000
0'
03
#990000
b11101010110110011000110000000 K
b11101010111001111001110000000 B
b110000 -
1'
13
#1000000
0'
03
#1010000
b110001 -
b11101010111001111001110000000 K
b11101010111101011010110000000 B
1'
13
#1020000
0'
03
#1030000
b11101010111101011010110000000 K
b11101011000000111011110000000 B
b110010 -
1'
13
#1040000
0'
03
#1050000
b110011 -
b11101011000000111011110000000 K
b11101011000100011100110000000 B
1'
13
#1060000
0'
03
#1070000
b11101011000100011100110000000 K
b11101011000111111101110000000 B
b110100 -
1'
13
#1080000
0'
03
#1090000
b110101 -
b11101011000111111101110000000 K
b11101011001011011110110000000 B
1'
13
#1100000
0'
03
#1110000
b11101011001011011110110000000 K
b11101011001110111111110000000 B
b110110 -
1'
13
#1120000
0'
03
#1130000
b110111 -
b11101011001110111111110000000 K
b11101011010010100000110000000 B
1'
13
#1140000
0'
03
#1150000
b11101011010010100000110000000 K
b11101011010110000001110000000 B
b111000 -
1'
13
#1160000
0'
03
#1170000
b111001 -
b11101011010110000001110000000 K
b11101011011001100010110000000 B
1'
13
#1180000
0'
03
#1190000
b11101011011001100010110000000 K
b11101011011101000011110000000 B
b111010 -
1'
13
#1200000
0'
03
#1210000
b111011 -
b11101011011101000011110000000 K
b11101011100000100100110000000 B
1'
13
#1220000
0'
03
#1230000
b11101011100000100100110000000 K
b11101011100100000101110000000 B
b111100 -
1'
13
#1240000
0'
03
#1250000
b111101 -
b11101011100100000101110000000 K
b11101011100111100110110000000 B
1'
13
#1260000
0'
03
#1270000
b11101011100111100110110000000 K
b11101011101011000111110000000 B
b111110 -
1'
13
#1280000
0'
03
#1290000
b111111 -
b11101011101011000111110000000 K
b11101011101110101000110000000 B
1'
13
#1300000
0'
03
#1310000
b11101011101110101000110000000 K
b11101011110010001001110000000 B
b1000000 -
1'
13
#1320000
0'
03
#1330000
b1000001 -
b11101011110010001001110000000 K
b11101011110101101010110000000 B
1'
13
#1340000
0'
03
#1350000
b11101011110101101010110000000 K
b11101011111001001011110000000 B
b1000010 -
1'
13
#1360000
0'
03
#1370000
b1000011 -
b11101011111001001011110000000 K
b11101011111100101100110000000 B
1'
13
#1380000
0'
03
#1390000
b11101011111100101100110000000 K
b11101100000000001101110000000 B
b1000100 -
1'
13
#1400000
0'
03
#1410000
b1000101 -
b11101100000000001101110000000 K
b11101100000011101110110000000 B
1'
13
#1420000
0'
03
#1430000
b11101100000011101110110000000 K
b11101100000111001111110000000 B
b1000110 -
1'
13
#1440000
0'
03
#1450000
b1000111 -
b11101100000111001111110000000 K
b11101100001010110000110000000 B
1'
13
#1460000
0'
03
#1470000
b11101100001010110000110000000 K
b11101100001110010001110000000 B
b1001000 -
1'
13
#1480000
0'
03
#1490000
b1001001 -
b11101100001110010001110000000 K
b11101100010001110010110000000 B
1'
13
#1500000
0'
03
#1510000
b11101100010001110010110000000 K
b11101100010101010011110000000 B
b1001010 -
1'
13
#1520000
0'
03
#1530000
b1001011 -
b11101100010101010011110000000 K
b11101100011000110100110000000 B
1'
13
#1540000
0'
03
#1550000
b11101100011000110100110000000 K
b11101100011100010101110000000 B
b1001100 -
1'
13
#1560000
0'
03
#1570000
b1001101 -
b11101100011100010101110000000 K
b11101100011111110110110000000 B
1'
13
#1580000
0'
03
#1590000
b11101100011111110110110000000 K
b11101100100011010111110000000 B
b1001110 -
1'
13
#1600000
0'
03
#1610000
b1001111 -
b11101100100011010111110000000 K
b11101100100110111000110000000 B
1'
13
#1620000
0'
03
#1630000
b11101100100110111000110000000 K
b11101100101010011001110000000 B
b1010000 -
1'
13
#1640000
0'
03
#1650000
b1010001 -
b11101100101010011001110000000 K
b11101100101101111010110000000 B
1'
13
#1660000
0'
03
#1670000
b11101100101101111010110000000 K
b11101100110001011011110000000 B
b1010010 -
1'
13
#1680000
0'
03
#1690000
b1010011 -
b11101100110001011011110000000 K
b11101100110100111100110000000 B
1'
13
#1700000
0'
03
#1710000
b11101100110100111100110000000 K
b11101100111000011101110000000 B
b1010100 -
1'
13
#1720000
0'
03
#1730000
b1010101 -
b11101100111000011101110000000 K
b11101100111011111110110000000 B
1'
13
#1740000
0'
03
#1750000
b11101100111011111110110000000 K
b11101100111111011111110000000 B
b1010110 -
1'
13
#1760000
0'
03
#1770000
b1010111 -
b11101100111111011111110000000 K
b11101101000011000000110000000 B
1'
13
#1780000
0'
03
#1790000
b11101101000011000000110000000 K
b11101101000110100001110000000 B
b1011000 -
1'
13
#1800000
0'
03
#1810000
b1011001 -
b11101101000110100001110000000 K
b11101101001010000010110000000 B
1'
13
#1820000
0'
03
#1830000
b11101101001010000010110000000 K
b11101101001101100011110000000 B
b1011010 -
1'
13
#1840000
0'
03
#1850000
b1011011 -
b11101101001101100011110000000 K
b11101101010001000100110000000 B
1'
13
#1860000
0'
03
#1870000
b11101101010001000100110000000 K
b11101101010100100101110000000 B
b1011100 -
1'
13
#1880000
0'
03
#1890000
b1011101 -
b11101101010100100101110000000 K
b11101101011000000110110000000 B
1'
13
#1900000
0'
03
#1910000
b11101101011000000110110000000 K
b11101101011011100111110000000 B
b1011110 -
1'
13
#1920000
0'
03
#1930000
b1011111 -
b11101101011011100111110000000 K
b11101101011111001000110000000 B
1'
13
#1940000
0'
03
#1950000
b11101101011111001000110000000 K
b11101101100010101001110000000 B
b1100000 -
1'
13
#1960000
0'
03
#1970000
b1100001 -
b11101101100010101001110000000 K
b11101101100110001010110000000 B
1'
13
#1980000
0'
03
#1990000
b11101101100110001010110000000 K
b11101101101001101011110000000 B
b1100010 -
1'
13
#2000000
0'
03
#2010000
b1100011 -
b11101101101001101011110000000 K
b11101101101101001100110000000 B
1'
13
#2020000
0'
03
#2030000
b11101101101101001100110000000 K
b11101101110000101101110000000 B
b1100100 -
1'
13
#2040000
0'
03
#2050000
b1100101 -
b11101101110000101101110000000 K
b11101101110100001110110000000 B
1'
13
#2060000
0'
03
#2070000
b11101101110100001110110000000 K
b11101101110111101111110000000 B
b1100110 -
1'
13
#2080000
0'
03
#2090000
b1100111 -
b11101101110111101111110000000 K
b11101101111011010000110000000 B
1'
13
#2100000
0'
03
#2110000
b11101101111011010000110000000 K
b11101101111110110001110000000 B
b1101000 -
1'
13
#2120000
0'
03
#2130000
b1101001 -
b11101101111110110001110000000 K
b11101110000010010010110000000 B
1'
13
#2140000
0'
03
#2150000
b11101110000010010010110000000 K
b11101110000101110011110000000 B
b1101010 -
1'
13
#2160000
0'
03
#2170000
b1101011 -
b11101110000101110011110000000 K
b11101110001001010100110000000 B
1'
13
#2180000
0'
03
#2190000
b11101110001001010100110000000 K
b11101110001100110101110000000 B
b1101100 -
1'
13
#2200000
0'
03
#2210000
b1101101 -
b11101110001100110101110000000 K
b11101110010000010110110000000 B
1'
13
#2220000
0'
03
#2230000
b11101110010000010110110000000 K
b11101110010011110111110000000 B
b1101110 -
1'
13
#2240000
0'
03
#2250000
b1101111 -
b11101110010011110111110000000 K
b11101110010111011000110000000 B
1'
13
#2260000
0'
03
#2270000
b11101110010111011000110000000 K
b11101110011010111001110000000 B
b1110000 -
1'
13
#2280000
0'
03
#2290000
b1110001 -
b11101110011010111001110000000 K
b11101110011110011010110000000 B
1'
13
#2300000
0'
03
#2310000
b11101110011110011010110000000 K
b11101110100001111011110000000 B
b1110010 -
1'
13
#2320000
0'
03
#2330000
b1110011 -
b11101110100001111011110000000 K
b11101110100101011100110000000 B
1'
13
#2340000
0'
03
#2350000
b11101110100101011100110000000 K
b11101110101000111101110000000 B
b1110100 -
1'
13
#2360000
0'
03
#2370000
b1110101 -
b11101110101000111101110000000 K
b11101110101100011110110000000 B
1'
13
#2380000
0'
03
#2390000
b11101110101100011110110000000 K
b11101110101111111111110000000 B
b1110110 -
1'
13
#2400000
0'
03
#2410000
b1110111 -
b11101110101111111111110000000 K
b11101110110011100000110000000 B
1'
13
#2420000
0'
03
#2430000
b11101110110011100000110000000 K
b11101110110111000001110000000 B
b1111000 -
1'
13
#2440000
0'
03
#2450000
b1111001 -
b11101110110111000001110000000 K
b11101110111010100010110000000 B
1'
13
#2460000
0'
03
#2470000
b11101110111010100010110000000 K
b11101110111110000011110000000 B
b1111010 -
1'
13
#2480000
0'
03
#2490000
b1111011 -
b11101110111110000011110000000 K
b11101111000001100100110000000 B
1'
13
#2500000
0'
03
#2510000
b11101111000001100100110000000 K
b11101111000101000101110000000 B
b1111100 -
1'
13
#2520000
0'
03
#2530000
b1111101 -
b11101111000101000101110000000 K
b11101111001000100110110000000 B
1'
13
#2540000
0'
03
#2550000
b11101111001000100110110000000 K
b11101111001100000111110000000 B
b1111110 -
1'
13
#2560000
0'
03
#2570000
b1111111 -
b11101111001100000111110000000 K
b11101111001111101000110000000 B
1'
13
#2580000
0'
03
#2590000
b11101111001111101000110000000 K
b11101111010011001001110000000 B
b10000000 -
1'
13
#2600000
0'
03
#2610000
b10000001 -
b11101111010011001001110000000 K
b11101111010110101010110000000 B
1'
13
#2620000
0'
03
#2630000
b11101111010110101010110000000 K
b11101111011010001011110000000 B
b10000010 -
1'
13
#2640000
0'
03
#2650000
b10000011 -
b11101111011010001011110000000 K
b11101111011101101100110000000 B
1'
13
#2660000
0'
03
#2670000
b11101111011101101100110000000 K
b11101111100001001101110000000 B
b10000100 -
1'
13
#2680000
0'
03
#2690000
b10000101 -
b11101111100001001101110000000 K
b11101111100100101110110000000 B
1'
13
#2700000
0'
03
#2710000
b11101111100100101110110000000 K
b11101111101000001111110000000 B
b10000110 -
1'
13
#2720000
0'
03
#2730000
b10000111 -
b11101111101000001111110000000 K
b11101111101011110000110000000 B
1'
13
#2740000
0'
03
#2750000
b11101111101011110000110000000 K
b11101111101111010001110000000 B
b10001000 -
1'
13
#2760000
0'
03
#2770000
b10001001 -
b11101111101111010001110000000 K
b11101111110010110010110000000 B
1'
13
#2780000
0'
03
#2790000
b11101111110010110010110000000 K
b11101111110110010011110000000 B
b10001010 -
1'
13
#2800000
0'
03
#2810000
b10001011 -
b11101111110110010011110000000 K
b11101111111001110100110000000 B
1'
13
#2820000
0'
03
#2830000
b11101111111001110100110000000 K
b11101111111101010101110000000 B
b10001100 -
1'
13
#2840000
0'
03
#2850000
b10001101 -
b11101111111101010101110000000 K
b11110000000000110110110000000 B
1'
13
#2860000
0'
03
#2870000
b11110000000000110110110000000 K
b11110000000100010111110000000 B
b10001110 -
1'
13
#2880000
0'
03
#2890000
b10001111 -
b11110000000100010111110000000 K
b11110000000111111000110000000 B
1'
13
#2900000
0'
03
#2910000
b11110000000111111000110000000 K
b11110000001011011001110000000 B
b10010000 -
1'
13
#2920000
0'
03
#2930000
b10010001 -
b11110000001011011001110000000 K
b11110000001110111010110000000 B
1'
13
#2940000
0'
03
#2950000
b11110000001110111010110000000 K
b11110000010010011011110000000 B
b10010010 -
1'
13
#2960000
0'
03
#2970000
b10010011 -
b11110000010010011011110000000 K
b11110000010101111100110000000 B
1'
13
#2980000
0'
03
#2990000
b11110000010101111100110000000 K
b11110000011001011101110000000 B
b10010100 -
1'
13
#3000000
0'
03
#3010000
b10010101 -
b11110000011001011101110000000 K
b11110000011100111110110000000 B
1'
13
#3020000
0'
03
#3030000
b11110000011100111110110000000 K
b11110000100000011111110000000 B
b10010110 -
1'
13
#3040000
0'
03
#3050000
b10010111 -
b11110000100000011111110000000 K
b11110000100100000000110000000 B
1'
13
#3060000
0'
03
#3070000
b11110000100100000000110000000 K
b11110000100111100001110000000 B
b10011000 -
1'
13
#3080000
0'
03
#3090000
b10011001 -
b11110000100111100001110000000 K
b11110000101011000010110000000 B
1'
13
#3100000
0'
03
#3110000
b11110000101011000010110000000 K
b11110000101110100011110000000 B
b10011010 -
1'
13
#3120000
0'
03
#3130000
b10011011 -
b11110000101110100011110000000 K
b11110000110010000100110000000 B
1'
13
#3140000
0'
03
#3150000
b11110000110010000100110000000 K
b11110000110101100101110000000 B
b10011100 -
1'
13
#3160000
0'
03
#3170000
b10011101 -
b11110000110101100101110000000 K
b11110000111001000110110000000 B
1'
13
#3180000
0'
03
#3190000
b11110000111001000110110000000 K
b11110000111100100111110000000 B
b10011110 -
1'
13
#3200000
0'
03
#3210000
b10011111 -
b11110000111100100111110000000 K
b11110001000000001000110000000 B
1'
13
#3220000
0'
03
#3230000
b11110001000000001000110000000 K
b11110001000011101001110000000 B
b10100000 -
1'
13
#3240000
0'
03
#3250000
b10100001 -
b11110001000011101001110000000 K
b11110001000111001010110000000 B
1'
13
#3260000
0'
03
#3270000
b11110001000111001010110000000 K
b11110001001010101011110000000 B
b10100010 -
1'
13
#3280000
0'
03
