hdl/uart/uart.v
module uart(
	// Outputs
	uart_busy,   // High means UART is transmitting
	uart_tx,     // UART transmit wire
	
	// Inputs
	uart_wr_i,   // Raise to transmit byte
	uart_dat_i,  // 8-bit data
	sys_clk_i,   // System clock, 50MHz
	sys_rst_i    // System reset
);

	input uart_wr_i;
	input [7:0] uart_dat_i;
	input sys_clk_i;
	input sys_rst_i;
  
	output uart_busy;
	output uart_tx;

	reg [3:0] bitcount;
	reg [8:0] shifter;
	reg uart_tx;

	wire uart_busy = |bitcount[3:1];
	wire sending = |bitcount;

	// sys_clk_i is 50MHz.  We want a 115200Hz clock

	reg [28:0] d;
	wire [28:0] dInc = d[28] ? (115200) : (115200 - 50000000);
	wire [28:0] dNxt = d + dInc;
	wire ser_clk = ~d[28];
  
	always @(posedge sys_clk_i)
		if (sys_rst_i) begin
			d = 0;
		end else begin
			d = dNxt;
		end

	always @(posedge sys_clk_i) begin
		if (sys_rst_i) begin
			uart_tx <= 1;
			bitcount <= 0;
			shifter <= 0;
		end else begin
		// just got a new byte
			if (uart_wr_i & ~uart_busy) begin
				shifter <= { uart_dat_i[7:0], 1'h0 };
				bitcount <= (1 + 8 + 2);
			end

			if (sending & ser_clk) begin
				{ shifter, uart_tx } <= { 1'h1 , shifter };
				bitcount <= bitcount - 1;
			end
			
		end
	end
  
endmodule

hdl/uart/peripheral_uart.v
module peripheral_uart(clk , rst , d_in , cs , addr , rd , wr, d_out,  uart_tx, ledout );
  
	input clk;
	input rst;
	input [15:0]d_in;
	input cs;
	input [3:0]addr; // 4 LSB from j1_io_addr
	input rd;
	input wr;
	
	output reg [15:0]d_out;
	output uart_tx;
	output reg ledout = 0;

	//---------------------------------- regs and wires-------------------------------

	reg [2:0] sel_mux; 	//selector mux_4  and demux_4
	reg [7:0] d_in_uart; // data in uart
	wire uart_busy;  // out_uart

	//------------------------------------ regs and wires-------------------------------

	//----address_decoder------------------
	always @(*) begin
		case (addr)
			4'h0:begin sel_mux = (cs && rd) ? 3'b001 : 3'b000; end //busy
			//Iría el data_in
			4'h2:begin sel_mux = (cs && wr) ? 3'b010 : 3'b000; end //data_out
			4'h4:begin sel_mux = (cs && wr) ? 3'b100 : 3'b000; end //ledout
			default:begin sel_mux = 3'b000; end
		endcase
	end
	//-----------------address_decoder--------------------

	//-------------------- escritura de registros
	always @(negedge clk) begin

		d_in_uart = (sel_mux[1]) ? d_in[7:0] : d_in_uart; // data in uart
		ledout = (sel_mux[2]) ? d_in[0] : ledout;	// write ledout register
		ledout = uart_busy;
	end
	//-------------------- escritura de registros

	//-----------------------mux_4 : multiplexa salidas del periferico
	always @(negedge clk) begin
		case (sel_mux)
			3'b001: d_out[0] = uart_busy;	// data out uart
			default: d_out = 0;
		endcase
	end
	//----------------------------------------------mux_4

										//(addr != 4'h4): se hace para evitar escrituras fantasma
	uart uart(.uart_busy(uart_busy), .uart_tx(uart_tx), .uart_wr_i(cs && wr && (addr != 4'h4) ), .uart_dat_i(d_in_uart), .sys_clk_i(clk), .sys_rst_i(rst));// System clock, 

endmodule

hdl/uart/peripheral_uart_TB.v
`timescale 1ns / 1ps

`define SIMULATION

module peripheral_uart_TB;

	reg clk;
	reg rst;
	reg [15:0]d_in;
	reg cs;
	reg [3:0]addr; // 4 LSB from j1_io_addr
	reg rd;
	reg wr;
	
	wire [15:0]d_out;
	wire uart_tx;
	wire ledout = 0;
	
	parameter PERIOD = 20;
	parameter real DUTY_CYCLE = 0.5;
	parameter OFFSET = 0;
	
	reg [20:0] i;
	event reset_trigger;
		
	peripheral_uart p_uart(.clk(clk) , .rst(rst) , .d_in(d_in) , .cs(cs) , .addr(addr) , .rd(rd) , .wr(wr) , .d_out(d_out) ,  .uart_tx(uart_tx) , .ledout(ledout) );
	
	initial begin// Initialize Inputs
		clk = 1;
		rst = 1;
		d_in = 0;
		cs = 0;
		addr = 3'b000;
		rd = 0;
		wr = 0;
	end

	initial begin// Process for sys_clk_i
		#OFFSET;
		forever begin
			clk = 1'b0;
			#(PERIOD-(PERIOD*DUTY_CYCLE)) clk = 1'b1;
			#(PERIOD*DUTY_CYCLE);
		end
	end
	
	initial begin
		@ (posedge clk)
		@ (posedge clk)
		rst = 0;
				
		for(i = 0; i < 10000; i = i+1) begin
			@ (posedge clk);
			
			if(i == 20) begin
				addr = 3'b010;
				cs = 1;
				wr = 1;
				rd = 0;
				d_in = 8'h26;
			end
			
			if(i == 25) begin
				addr = 3'b010;
				cs = 1;
				wr = 1;
				rd = 0;
				d_in = 8'h0;
			end
			
			if(i == 30) begin
				addr = 3'b000;
				cs = 0;
				wr = 0;
				rd = 0;
			end
			
			if(i == 7000) begin
				addr = 3'b010;
				cs = 1;
				wr = 1;
				rd = 0;
				d_in = 8'h2D;
			end
			
			if(i == 7005) begin
				addr = 3'b010;
				cs = 1;
				wr = 1;
				rd = 0;
				d_in = 8'h0;
			end
			
			if(i == 7010) begin
				addr = 3'b000;
				cs = 0;
				wr = 0;
				rd = 0;
			end
			
		end
	end
	
	initial begin: TEST_CASE
	  	$dumpfile("peripheral_uart_TB.vcd");
	  	$dumpvars(-1, peripheral_uart_TB);
	
	  	#10 -> reset_trigger;
	  	#((PERIOD*DUTY_CYCLE)*30000) $finish;
	end

endmodule

hdl/uart/simulation/peripheral_uart_TB.vcd
$date
	Sun Jun 14 17:46:00 2015
$end
$version
	Icarus Verilog
$end
$timescale
	1ps
$end
$scope module peripheral_uart_TB $end
$var event 1 ! reset_trigger $end
$var wire 16 " d_out [15:0] $end
$var wire 1 # ledout $end
$var wire 1 $ uart_tx $end
$var reg 4 % addr [3:0] $end
$var reg 1 & clk $end
$var reg 1 ' cs $end
$var reg 16 ( d_in [15:0] $end
$var reg 21 ) i [20:0] $end
$var reg 1 * rd $end
$var reg 1 + rst $end
$var reg 1 , wr $end
$scope module p_uart $end
$var wire 4 - addr [3:0] $end
$var wire 1 . clk $end
$var wire 1 / cs $end
$var wire 16 0 d_in [15:0] $end
$var wire 1 1 rd $end
$var wire 1 2 rst $end
$var wire 1 3 uart_busy $end
$var wire 1 $ uart_tx $end
$var wire 1 4 wr $end
$var reg 8 5 d_in_uart [7:0] $end
$var reg 16 6 d_out [15:0] $end
$var reg 1 7 ledout $end
$var reg 3 8 sel_mux [2:0] $end
$scope module uart $end
$var wire 29 9 dInc [28:0] $end
$var wire 29 : dNxt [28:0] $end
$var wire 1 ; sending $end
$var wire 1 < ser_clk $end
$var wire 1 . sys_clk_i $end
$var wire 1 2 sys_rst_i $end
$var wire 1 3 uart_busy $end
$var wire 8 = uart_dat_i [7:0] $end
$var wire 1 > uart_wr_i $end
$var reg 4 ? bitcount [3:0] $end
$var reg 29 @ d [28:0] $end
$var reg 9 A shifter [8:0] $end
$var reg 1 B uart_tx $end
$upscope $end
$upscope $end
$scope begin TEST_CASE $end
$upscope $end
$upscope $end
$enddefinitions $end
#0
$dumpvars
1B
b0 A
b0 @
b0 ?
0>
bx =
1<
0;
b11101000001101101000110000000 :
b11101000001101101000110000000 9
b0 8
x7
b0 6
bx 5
04
03
12
01
b0 0
0/
0.
b0 -
0,
1+
0*
bx )
b0 (
0'
0&
b0 %
1$
x#
b0 "
1!
$end
#10000
1&
1.
1!
#20000
07
0#
0&
0.
#30000
b11100001000000000 9
0<
b11101000001101101000110000000 @
b11101000010001001001110000000 :
b0 )
0+
02
1&
1.
#40000
0&
0.
#50000
b1 )
b11101000010001001001110000000 @
b11101000010100101010110000000 :
1&
1.
#60000
0&
0.
#70000
b11101000010100101010110000000 @
b11101000011000001011110000000 :
b10 )
1&
1.
#80000
0&
0.
#90000
b11 )
b11101000011000001011110000000 @
b11101000011011101100110000000 :
1&
1.
#100000
0&
0.
#110000
b11101000011011101100110000000 @
b11101000011111001101110000000 :
b100 )
1&
1.
#120000
0&
0.
#130000
b101 )
b11101000011111001101110000000 @
b11101000100010101110110000000 :
1&
1.
#140000
0&
0.
#150000
b11101000100010101110110000000 @
b11101000100110001111110000000 :
b110 )
1&
1.
#160000
0&
0.
#170000
b111 )
b11101000100110001111110000000 @
b11101000101001110000110000000 :
1&
1.
#180000
0&
0.
#190000
b11101000101001110000110000000 @
b11101000101101010001110000000 :
b1000 )
1&
1.
#200000
0&
0.
#210000
b1001 )
b11101000101101010001110000000 @
b11101000110000110010110000000 :
1&
1.
#220000
0&
0.
#230000
b11101000110000110010110000000 @
b11101000110100010011110000000 :
b1010 )
1&
1.
#240000
0&
0.
#250000
b1011 )
b11101000110100010011110000000 @
b11101000110111110100110000000 :
1&
1.
#260000
0&
0.
#270000
b11101000110111110100110000000 @
b11101000111011010101110000000 :
b1100 )
1&
1.
#280000
0&
0.
#290000
b1101 )
b11101000111011010101110000000 @
b11101000111110110110110000000 :
1&
1.
#300000
0&
0.
#310000
b11101000111110110110110000000 @
b11101001000010010111110000000 :
b1110 )
1&
1.
#320000
0&
0.
#330000
b1111 )
b11101001000010010111110000000 @
b11101001000101111000110000000 :
1&
1.
#340000
0&
0.
#350000
b11101001000101111000110000000 @
b11101001001001011001110000000 :
b10000 )
1&
1.
#360000
0&
0.
#370000
b10001 )
b11101001001001011001110000000 @
b11101001001100111010110000000 :
1&
1.
#380000
0&
0.
#390000
b11101001001100111010110000000 @
b11101001010000011011110000000 :
b10010 )
1&
1.
#400000
0&
0.
#410000
b10011 )
b11101001010000011011110000000 @
b11101001010011111100110000000 :
1&
1.
#420000
0&
0.
#430000
b11101001010011111100110000000 @
b11101001010111011101110000000 :
b10100 )
1&
1.
#440000
0&
0.
#450000
1>
b10 8
b10101 )
b100110 (
b100110 0
1,
14
1'
1/
b10 %
b10 -
b11101001010111011101110000000 @
b11101001011010111110110000000 :
1&
1.
#460000
b100110 5
b100110 =
0&
0.
#470000
13
b1011 ?
1;
b1001100 A
b11101001011010111110110000000 @
b11101001011110011111110000000 :
b10110 )
1&
1.
#480000
17
x#
0&
0.
#490000
b10111 )
b11101001011110011111110000000 @
b11101001100010000000110000000 :
1&
1.
#500000
0&
0.
#510000
b11101001100010000000110000000 @
b11101001100101100001110000000 :
b11000 )
1&
1.
#520000
0&
0.
#530000
b11001 )
b11101001100101100001110000000 @
b11101001101001000010110000000 :
1&
1.
#540000
0&
0.
#550000
b11101001101001000010110000000 @
b11101001101100100011110000000 :
b11010 )
b0 (
b0 0
1&
1.
#560000
b0 5
b0 =
0&
0.
#570000
b11011 )
b11101001101100100011110000000 @
b11101001110000000100110000000 :
1&
1.
#580000
0&
0.
#590000
b11101001110000000100110000000 @
b11101001110011100101110000000 :
b11100 )
1&
1.
#600000
0&
0.
#610000
b11101 )
b11101001110011100101110000000 @
b11101001110111000110110000000 :
1&
1.
#620000
0&
0.
#630000
b11101001110111000110110000000 @
b11101001111010100111110000000 :
b11110 )
1&
1.
#640000
0&
0.
#650000
0>
b0 8
b11111 )
0,
04
0'
0/
b0 %
b0 -
b11101001111010100111110000000 @
b11101001111110001000110000000 :
1&
1.
#660000
0&
0.
#670000
b11101001111110001000110000000 @
b11101010000001101001110000000 :
b100000 )
1&
1.
#680000
0&
0.
#690000
b100001 )
b11101010000001101001110000000 @
b11101010000101001010110000000 :
1&
1.
#700000
0&
0.
#710000
b11101010000101001010110000000 @
b11101010001000101011110000000 :
b100010 )
1&
1.
#720000
0&
0.
#730000
b100011 )
b11101010001000101011110000000 @
b11101010001100001100110000000 :
1&
1.
#740000
0&
0.
#750000
b11101010001100001100110000000 @
b11101010001111101101110000000 :
b100100 )
1&
1.
#760000
0&
0.
#770000
b100101 )
b11101010001111101101110000000 @
b11101010010011001110110000000 :
1&
1.
#780000
0&
0.
#790000
b11101010010011001110110000000 @
b11101010010110101111110000000 :
b100110 )
1&
1.
#800000
0&
0.
#810000
b100111 )
b11101010010110101111110000000 @
b11101010011010010000110000000 :
1&
1.
#820000
0&
0.
#830000
b11101010011010010000110000000 @
b11101010011101110001110000000 :
b101000 )
1&
1.
#840000
0&
0.
#850000
b101001 )
b11101010011101110001110000000 @
b11101010100001010010110000000 :
1&
1.
#860000
0&
0.
#870000
b11101010100001010010110000000 @
b11101010100100110011110000000 :
b101010 )
1&
1.
#880000
0&
0.
#890000
b101011 )
b11101010100100110011110000000 @
b11101010101000010100110000000 :
1&
1.
#900000
0&
0.
#910000
b11101010101000010100110000000 @
b11101010101011110101110000000 :
b101100 )
1&
1.
#920000
0&
0.
#930000
b101101 )
b11101010101011110101110000000 @
b11101010101111010110110000000 :
1&
1.
#940000
0&
0.
#950000
b11101010101111010110110000000 @
b11101010110010110111110000000 :
b101110 )
1&
1.
#960000
0&
0.
#970000
b101111 )
b11101010110010110111110000000 @
b11101010110110011000110000000 :
1&
1.
#980000
0&
0.
#990000
b11101010110110011000110000000 @
b11101010111001111001110000000 :
b110000 )
1&
1.
#1000000
0&
0.
#1010000
b110001 )
b11101010111001111001110000000 @
b11101010111101011010110000000 :
1&
1.
#1020000
0&
0.
#1030000
b11101010111101011010110000000 @
b11101011000000111011110000000 :
b110010 )
1&
1.
#1040000
0&
0.
#1050000
b110011 )
b11101011000000111011110000000 @
b11101011000100011100110000000 :
1&
1.
#1060000
0&
0.
#1070000
b11101011000100011100110000000 @
b11101011000111111101110000000 :
b110100 )
1&
1.
#1080000
0&
0.
#1090000
b110101 )
b11101011000111111101110000000 @
b11101011001011011110110000000 :
1&
1.
#1100000
0&
0.
#1110000
b11101011001011011110110000000 @
b11101011001110111111110000000 :
b110110 )
1&
1.
#1120000
0&
0.
#1130000
b110111 )
b11101011001110111111110000000 @
b11101011010010100000110000000 :
1&
1.
#1140000
0&
0.
#1150000
b11101011010010100000110000000 @
b11101011010110000001110000000 :
b111000 )
1&
1.
#1160000
0&
0.
#1170000
b111001 )
b11101011010110000001110000000 @
b11101011011001100010110000000 :
1&
1.
#1180000
0&
0.
#1190000
b11101011011001100010110000000 @
b11101011011101000011110000000 :
b111010 )
1&
1.
#1200000
0&
0.
#1210000
b111011 )
b11101011011101000011110000000 @
b11101011100000100100110000000 :
1&
1.
#1220000
0&
0.
#1230000
b11101011100000100100110000000 @
b11101011100100000101110000000 :
b111100 )
1&
1.
#1240000
0&
0.
#1250000
b111101 )
b11101011100100000101110000000 @
b11101011100111100110110000000 :
1&
1.
#1260000
0&
0.
#1270000
b11101011100111100110110000000 @
b11101011101011000111110000000 :
b111110 )
1&
1.
#1280000
0&
0.
#1290000
b111111 )
b11101011101011000111110000000 @
b11101011101110101000110000000 :
1&
1.
#1300000
0&
0.
#1310000
b11101011101110101000110000000 @
b11101011110010001001110000000 :
b1000000 )
1&
1.
#1320000
0&
0.
#1330000
b1000001 )
b11101011110010001001110000000 @
b11101011110101101010110000000 :
1&
1.
#1340000
0&
0.
#1350000
b11101011110101101010110000000 @
b11101011111001001011110000000 :
b1000010 )
1&
1.
#1360000
0&
0.
#1370000
b1000011 )
b11101011111001001011110000000 @
b11101011111100101100110000000 :
1&
1.
#1380000
0&
0.
#1390000
b11101011111100101100110000000 @
b11101100000000001101110000000 :
b1000100 )
1&
1.
#1400000
0&
0.
#1410000
b1000101 )
b11101100000000001101110000000 @
b11101100000011101110110000000 :
1&
1.
#1420000
0&
0.
#1430000
b11101100000011101110110000000 @
b11101100000111001111110000000 :
b1000110 )
1&
1.
#1440000
0&
0.
#1450000
b1000111 )
b11101100000111001111110000000 @
b11101100001010110000110000000 :
1&
1.
#1460000
0&
0.
#1470000
b11101100001010110000110000000 @
b11101100001110010001110000000 :
b1001000 )
1&
1.
#1480000
0&
0.
#1490000
b1001001 )
b11101100001110010001110000000 @
b11101100010001110010110000000 :
1&
1.
#1500000
0&
0.
#1510000
b11101100010001110010110000000 @
b11101100010101010011110000000 :
b1001010 )
1&
1.
#1520000
0&
0.
#1530000
b1001011 )
b11101100010101010011110000000 @
b11101100011000110100110000000 :
1&
1.
#1540000
0&
0.
#1550000
b11101100011000110100110000000 @
b11101100011100010101110000000 :
b1001100 )
1&
1.
#1560000
0&
0.
#1570000
b1001101 )
b11101100011100010101110000000 @
b11101100011111110110110000000 :
1&
1.
#1580000
0&
0.
#1590000
b11101100011111110110110000000 @
b11101100100011010111110000000 :
b1001110 )
1&
1.
#1600000
0&
0.
#1610000
b1001111 )
b11101100100011010111110000000 @
b11101100100110111000110000000 :
1&
1.
#1620000
0&
0.
#1630000
b11101100100110111000110000000 @
b11101100101010011001110000000 :
b1010000 )
1&
1.
#1640000
0&
0.
#1650000
b1010001 )
b11101100101010011001110000000 @
b11101100101101111010110000000 :
1&
1.
#1660000
0&
0.
#1670000
b11101100101101111010110000000 @
b11101100110001011011110000000 :
b1010010 )
1&
1.
#1680000
0&
0.
#1690000
b1010011 )
b11101100110001011011110000000 @
b11101100110100111100110000000 :
1&
1.
#1700000
0&
0.
#1710000
b11101100110100111100110000000 @
b11101100111000011101110000000 :
b1010100 )
1&
1.
#1720000
0&
0.
#1730000
b1010101 )
b11101100111000011101110000000 @
b11101100111011111110110000000 :
1&
1.
#1740000
0&
0.
#1750000
b11101100111011111110110000000 @
b11101100111111011111110000000 :
b1010110 )
1&
1.
#1760000
0&
0.
#1770000
b1010111 )
b11101100111111011111110000000 @
b11101101000011000000110000000 :
1&
1.
#1780000
0&
0.
#1790000
b11101101000011000000110000000 @
b11101101000110100001110000000 :
b1011000 )
1&
1.
#1800000
0&
0.
#1810000
b1011001 )
b11101101000110100001110000000 @
b11101101001010000010110000000 :
1&
1.
#1820000
0&
0.
#1830000
b11101101001010000010110000000 @
b11101101001101100011110000000 :
b1011010 )
1&
1.
#1840000
0&
0.
#1850000
b1011011 )
b11101101001101100011110000000 @
b11101101010001000100110000000 :
1&
1.
#1860000
0&
0.
#1870000
b11101101010001000100110000000 @
b11101101010100100101110000000 :
b1011100 )
1&
1.
#1880000
0&
0.
#1890000
b1011101 )
b11101101010100100101110000000 @
b11101101011000000110110000000 :
1&
1.
#1900000
0&
0.
#1910000
b11101101011000000110110000000 @
b11101101011011100111110000000 :
b1011110 )
1&
1.
#1920000
0&
0.
#1930000
b1011111 )
b11101101011011100111110000000 @
b11101101011111001000110000000 :
1&
1.
#1940000
0&
0.
#1950000
b11101101011111001000110000000 @
b11101101100010101001110000000 :
b1100000 )
1&
1.
#1960000
0&
0.
#1970000
b1100001 )
b11101101100010101001110000000 @
b11101101100110001010110000000 :
1&
1.
#1980000
0&
0.
#1990000
b11101101100110001010110000000 @
b11101101101001101011110000000 :
b1100010 )
1&
1.
#2000000
0&
0.
#2010000
b1100011 )
b11101101101001101011110000000 @
b11101101101101001100110000000 :
1&
1.
#2020000
0&
0.
#2030000
b11101101101101001100110000000 @
b11101101110000101101110000000 :
b1100100 )
1&
1.
#2040000
0&
0.
#2050000
b1100101 )
b11101101110000101101110000000 @
b11101101110100001110110000000 :
1&
1.
#2060000
0&
0.
#2070000
b11101101110100001110110000000 @
b11101101110111101111110000000 :
b1100110 )
1&
1.
#2080000
0&
0.
#2090000
b1100111 )
b11101101110111101111110000000 @
b11101101111011010000110000000 :
1&
1.
#2100000
0&
0.
#2110000
b11101101111011010000110000000 @
b11101101111110110001110000000 :
b1101000 )
1&
1.
#2120000
0&
0.
#2130000
b1101001 )
b11101101111110110001110000000 @
b11101110000010010010110000000 :
1&
1.
#2140000
0&
0.
#2150000
b11101110000010010010110000000 @
b11101110000101110011110000000 :
b1101010 )
1&
1.
#2160000
0&
0.
#2170000
b1101011 )
b11101110000101110011110000000 @
b11101110001001010100110000000 :
1&
1.
#2180000
0&
0.
#2190000
b11101110001001010100110000000 @
b11101110001100110101110000000 :
b1101100 )
1&
1.
#2200000
0&
0.
#2210000
b1101101 )
b11101110001100110101110000000 @
b11101110010000010110110000000 :
1&
1.
#2220000
0&
0.
#2230000
b11101110010000010110110000000 @
b11101110010011110111110000000 :
b1101110 )
1&
1.
#2240000
0&
0.
#2250000
b1101111 )
b11101110010011110111110000000 @
b11101110010111011000110000000 :
1&
1.
#2260000
0&
0.
#2270000
b11101110010111011000110000000 @
b11101110011010111001110000000 :
b1110000 )
1&
1.
#2280000
0&
0.
#2290000
b1110001 )
b11101110011010111001110000000 @
b11101110011110011010110000000 :
1&
1.
#2300000
0&
0.
#2310000
b11101110011110011010110000000 @
b11101110100001111011110000000 :
b1110010 )
1&
1.
#2320000
0&
0.
#2330000
b1110011 )
b11101110100001111011110000000 @
b11101110100101011100110000000 :
1&
1.
#2340000
0&
0.
#2350000
b11101110100101011100110000000 @
b11101110101000111101110000000 :
b1110100 )
1&
1.
#2360000
0&
0.
#2370000
b1110101 )
b11101110101000111101110000000 @
b11101110101100011110110000000 :
1&
1.
#2380000
0&
0.
#2390000
b11101110101100011110110000000 @
b11101110101111111111110000000 :
b1110110 )
1&
1.
#2400000
0&
0.
#2410000
b1110111 )
b11101110101111111111110000000 @
b11101110110011100000110000000 :
1&
1.
#2420000
0&
0.
#2430000
b11101110110011100000110000000 @
b11101110110111000001110000000 :
b1111000 )
1&
1.
#2440000
0&
0.
#2450000
b1111001 )
b11101110110111000001110000000 @
b11101110111010100010110000000 :
1&
1.
#2460000
0&
0.
#2470000
b11101110111010100010110000000 @
b11101110111110000011110000000 :
b1111010 )
1&
1.
#2480000
0&
0.
#2490000
b1111011 )
b11101110111110000011110000000 @
b11101111000001100100110000000 :
1&
1.
#2500000
0&
0.
#2510000
b11101111000001100100110000000 @
b11101111000101000101110000000 :
b1111100 )
1&
1.
#2520000
0&
0.
#2530000
b1111101 )
b11101111000101000101110000000 @
b11101111001000100110110000000 :
1&
1.
#2540000
0&
0.
#2550000
b11101111001000100110110000000 @
b11101111001100000111110000000 :
b1111110 )
1&
1.
#2560000
0&
0.
#2570000
b1111111 )
b11101111001100000111110000000 @
b11101111001111101000110000000 :
1&
1.
#2580000
0&
0.
#2590000
b11101111001111101000110000000 @
b11101111010011001001110000000 :
b10000000 )
1&
1.
#2600000
0&
0.
#2610000
b10000001 )
b11101111010011001001110000000 @
b11101111010110101010110000000 :
1&
1.
#2620000
0&
0.
#2630000
b11101111010110101010110000000 @
b11101111011010001011110000000 :
b10000010 )
1&
1.
#2640000
0&
0.
#2650000
b10000011 )
b11101111011010001011110000000 @
b11101111011101101100110000000 :
1&
1.
#2660000
0&
0.
#2670000
b11101111011101101100110000000 @
b11101111100001001101110000000 :
b10000100 )
1&
1.
#2680000
0&
0.
#2690000
b10000101 )
b11101111100001001101110000000 @
b11101111100100101110110000000 :
1&
1.
#2700000
0&
0.
#2710000
b11101111100100101110110000000 @
b11101111101000001111110000000 :
b10000110 )
1&
1.
#2720000
0&
0.
#2730000
b10000111 )
b11101111101000001111110000000 @
b11101111101011110000110000000 :
1&
1.
#2740000
0&
0.
#2750000
b11101111101011110000110000000 @
b11101111101111010001110000000 :
b10001000 )
1&
1.
#2760000
0&
0.
#2770000
b10001001 )
b11101111101111010001110000000 @
b11101111110010110010110000000 :
1&
1.
#2780000
0&
0.
#2790000
b11101111110010110010110000000 @
b11101111110110010011110000000 :
b10001010 )
1&
1.
#2800000
0&
0.
#2810000
b10001011 )
b11101111110110010011110000000 @
b11101111111001110100110000000 :
1&
1.
#2820000
0&
0.
#2830000
b11101111111001110100110000000 @
b11101111111101010101110000000 :
b10001100 )
1&
1.
#2840000
0&
0.
#2850000
b10001101 )
b11101111111101010101110000000 @
b11110000000000110110110000000 :
1&
1.
#2860000
0&
0.
#2870000
b11110000000000110110110000000 @
b11110000000100010111110000000 :
b10001110 )
1&
1.
#2880000
0&
0.
#2890000
b10001111 )
b11110000000100010111110000000 @
b11110000000111111000110000000 :
1&
1.
#2900000
0&
0.
#2910000
b11110000000111111000110000000 @
b11110000001011011001110000000 :
b10010000 )
1&
1.
#2920000
0&
0.
#2930000
b10010001 )
b11110000001011011001110000000 @
b11110000001110111010110000000 :
1&
1.
#2940000
0&
0.
#2950000
b11110000001110111010110000000 @
b11110000010010011011110000000 :
b10010010 )
1&
1.
#2960000
0&
0.
#2970000
b10010011 )
b11110000010010011011110000000 @
b11110000010101111100110000000 :
1&
1.
#2980000
0&
0.
#2990000
b11110000010101111100110000000 @
b11110000011001011101110000000 :
b10010100 )
1&
1.
#3000000
0&
0.
#3010000
b10010101 )
b11110000011001011101110000000 @
b11110000011100111110110000000 :
1&
1.
#3020000
0&
0.
#3030000
b11110000011100111110110000000 @
b11110000100000011111110000000 :
b10010110 )
1&
1.
#3040000
0&
0.
#3050000
b10010111 )
b11110000100000011111110000000 @
b11110000100100000000110000000 :
1&
1.
#3060000
0&
0.
#3070000
b11110000100100000000110000000 @
b11110000100111100001110000000 :
b10011000 )
1&
1.
#3080000
0&
0.
#3090000
b10011001 )
b11110000100111100001110000000 @
b11110000101011000010110000000 :
1&
1.
#3100000
0&
0.
#3110000
b11110000101011000010110000000 @
b11110000101110100011110000000 :
b10011010 )
1&
1.
#3120000
0&
0.
#3130000
b10011011 )
b11110000101110100011110000000 @
b11110000110010000100110000000 :
1&
1.
#3140000
0&
0.
#3150000
b11110000110010000100110000000 @
b11110000110101100101110000000 :
b10011100 )
1&
1.
#3160000
0&
0.
#3170000
b10011101 )
b11110000110101100101110000000 @
b11110000111001000110110000000 :
1&
1.
#3180000
0&
0.
#3190000
b11110000111001000110110000000 @
b11110000111100100111110000000 :
b10011110 )
1&
1.
#3200000
0&
0.
#3210000
b10011111 )
b11110000111100100111110000000 @
b11110001000000001000110000000 :
1&
1.
#3220000
0&
0.
#3230000
b11110001000000001000110000000 @
b11110001000011101001110000000 :
b10100000 )
1&
1.
#3240000
0&
0.
#3250000
b10100001 )
b11110001000011101001110000000 @
b11110001000111001010110000000 :
1&
1.
#3260000
0&
0.
#3270000
b11110001000111001010110000000 @
b11110001001010101011110000000 :
b10100010 )
1&
1.
#3280000
0&
0.
#3290000
b10100011 )
b11110001001010101011110000000 @
b11110001001110001100110000000 :
1&
1.
#3300000
0&
0.
#3310000
b11110001001110001100110000000 @
b11110001010001101101110000000 :
b10100100 )
1&
1.
#3320000
0&
0.
#3330000
b10100101 )
b11110001010001101101110000000 @
b11110001010101001110110000000 :
1&
1.
#3340000
0&
0.
#3350000
b11110001010101001110110000000 @
b11110001011000101111110000000 :
b10100110 )
1&
1.
#3360000
0&
0.
#3370000
b10100111 )
b11110001011000101111110000000 @
b11110001011100010000110000000 :
1&
1.
#3380000
0&
0.
#3390000
b11110001011100010000110000000 @
b11110001011111110001110000000 :
b10101000 )
1&
1.
#3400000
0&
0.
#3410000
b10101001 )
b11110001011111110001110000000 @
b11110001100011010010110000000 :
1&
1.
#3420000
0&
0.
#3430000
b11110001100011010010110000000 @
b11110001100110110011110000000 :
b10101010 )
1&
1.
#3440000
0&
0.
#3450000
b10101011 )
b11110001100110110011110000000 @
b11110001101010010100110000000 :
1&
1.
#3460000
0&
0.
#3470000
b11110001101010010100110000000 @
b11110001101101110101110000000 :
b10101100 )
1&
1.
#3480000
0&
0.
#3490000
b10101101 )
b11110001101101110101110000000 @
b11110001110001010110110000000 :
1&
1.
#3500000
0&
0.
#3510000
b11110001110001010110110000000 @
b11110001110100110111110000000 :
b10101110 )
1&
1.
#3520000
0&
0.
#3530000
b10101111 )
b11110001110100110111110000000 @
b11110001111000011000110000000 :
1&
1.
#3540000
0&
0.
#3550000
b11110001111000011000110000000 @
b11110001111011111001110000000 :
b10110000 )
1&
1.
#3560000
0&
0.
#3570000
b10110001 )
b11110001111011111001110000000 @
b11110001111111011010110000000 :
1&
1.
#3580000
0&
0.
#3590000
b11110001111111011010110000000 @
b11110010000010111011110000000 :
b10110010 )
1&
1.
#3600000
0&
0.
#3610000
b10110011 )
b11110010000010111011110000000 @
b11110010000110011100110000000 :
1&
1.
#3620000
0&
0.
#3630000
b11110010000110011100110000000 @
b11110010001001111101110000000 :
b10110100 )
1&
1.
#3640000
0&
0.
#3650000
b10110101 )
b11110010001001111101110000000 @
b11110010001101011110110000000 :
1&
1.
#3660000
0&
0.
#3670000
b11110010001101011110110000000 @
b11110010010000111111110000000 :
b10110110 )
1&
1.
#3680000
0&
0.
#3690000
b10110111 )
b11110010010000111111110000000 @
b11110010010100100000110000000 :
1&
1.
#3700000
0&
0.
#3710000
b11110010010100100000110000000 @
b11110010011000000001110000000 :
b10111000 )
1&
1.
#3720000
0&
0.
#3730000
b10111001 )
b11110010011000000001110000000 @
b11110010011011100010110000000 :
1&
1.
#3740000
0&
0.
#3750000
b11110010011011100010110000000 @
b11110010011111000011110000000 :
b10111010 )
1&
1.
#3760000
0&
0.
#3770000
b10111011 )
b11110010011111000011110000000 @
b11110010100010100100110000000 :
1&
1.
#3780000
0&
0.
#3790000
b11110010100010100100110000000 @
b11110010100110000101110000000 :
b10111100 )
1&
1.
#3800000
0&
0.
#3810000
b10111101 )
b11110010100110000101110000000 @
b11110010101001100110110000000 :
1&
1.
#3820000
0&
0.
#3830000
b11110010101001100110110000000 @
b11110010101101000111110000000 :
b10111110 )
1&
1.
#3840000
0&
0.
#3850000
b10111111 )
b11110010101101000111110000000 @
b11110010110000101000110000000 :
1&
1.
#3860000
0&
0.
#3870000
b11110010110000101000110000000 @
b11110010110100001001110000000 :
b11000000 )
1&
1.
#3880000
0&
0.
#3890000
b11000001 )
b11110010110100001001110000000 @
b11110010110111101010110000000 :
1&
1.
#3900000
0&
0.
#3910000
b11110010110111101010110000000 @
b11110010111011001011110000000 :
b11000010 )
1&
1.
#3920000
0&
0.
#3930000
b11000011 )
b11110010111011001011110000000 @
b11110010111110101100110000000 :
1&
1.
#3940000
0&
0.
#3950000
b11110010111110101100110000000 @
b11110011000010001101110000000 :
b11000100 )
1&
1.
#3960000
0&
0.
#3970000
b11000101 )
b11110011000010001101110000000 @
b11110011000101101110110000000 :
1&
1.
#3980000
0&
0.
#3990000
b11110011000101101110110000000 @
b11110011001001001111110000000 :
b11000110 )
1&
1.
#4000000
0&
0.
