hdl/multiplier/mult_32/control_mult.v
module control_mult( clk , rst , lsb_B , init , z , done , sh , reset , add );
	input clk;
	input rst;
	input lsb_B;
	input init; 
	input z;

	output reg done;
	output reg sh;
	output reg reset;
	output reg add;

	parameter START		= 3'b000;
	parameter CHECK		= 3'b001;
 	parameter SHIFT		= 3'b010;
	parameter ADD			= 3'b011;
	parameter END			= 3'b100;
 
	reg [2:0] state;
 
	initial begin
		done = 0;
		sh = 0;
		reset = 0;
		add = 0;
		state = 0;
	end

	reg [3:0] count;

	always @(posedge clk) begin
		if (rst)
			state = START;
		else begin
			case(state)
				START:begin
					count=0;
					if(init)
						state = CHECK;
					else
						state = START;
 				end

				CHECK:
					if(lsb_B)
						state = ADD;
					else
						state = SHIFT;

				SHIFT: 
					if(z)
						state = END;
					else
						state = CHECK;
 	
				ADD: 
					state = SHIFT;
	
				END:begin
					count = count + 1;
					state = (count > 9) ? START : END ; // hace falta de 10 ciclos de reloj, para que lea el done y luego cargue el resultado
				end

				default: state = START;
			endcase
		end
	end


	always @(state) begin
		case(state)
			START:begin
				done = 0;
				sh = 0;
				reset = 1;
				add = 0;
			end
 			
 			CHECK:begin
				done = 0;
				sh = 0;
				reset = 0;
				add = 0;
			end
			
			SHIFT:begin
				done = 0;
				sh = 1;
				reset = 0;
				add = 0;
			end

			ADD:begin
				done = 0;
				sh = 0;
				reset = 0;
				add = 1;
			end
			END:begin
				done = 1;
				sh = 0;
				reset = 0;
				add = 0;
			end
			default:begin
				done = 0;
				sh = 0;
				reset = 0;
				add = 0;
			end
		endcase
	end
endmodule

hdl/multiplier/mult_32/comp.v
module comp(B, z);
	input [15:0] B;
	output z;
	reg tmp;
	
	initial tmp = 0;
	assign z = tmp;

	always@(*)
		tmp = (B==0) ? 1'b1 : 1'b0;
endmodule

hdl/multiplier/mult_32/acc.v
module acc (clk , A, add, rst, pp);
	input clk;
	input [31:0] A;
	input add;
	input rst; 
	output reg [31:0] pp;

	initial pp = 0;

	always @(negedge clk)
		if (rst) 
			pp = 32'h00000000;
		else begin
			if (add) pp = pp + A;
			else pp = pp;
		end
endmodule

hdl/multiplier/mult_32/lsr.v
module lsr (clk , in_A , shift , load , s_A);
	input clk;
	input [15:0] in_A;
	input load;
	input shift;
	output reg [30:0] s_A;

	always @(negedge clk)
		if(load)
			s_A = in_A ;
		else begin
			if(shift) s_A = s_A << 1 ;
			else	s_A = s_A;
		end
endmodule

hdl/multiplier/mult_32/rsr.v
module rsr (clk, in_B , shift , load , s_B);
	input clk;
	input [15:0] in_B;
	input load;
	input shift;
	output reg [15:0] s_B;

	always @(negedge clk)
		if(load)
			s_B = in_B ;
		else begin
			if(shift)
				s_B = s_B >> 1;
			else
				s_B = s_B;
		end
endmodule

hdl/multiplier/mult_32/mult_32.v
module mult_32(clk , rst , init , A , B , pp , done);
	input rst;
	input clk;
	input init;
	input [15:0] A;
	input [15:0] B;
	output [31:0] pp;
	output done;

	wire w_sh;
	wire w_reset;
	wire w_add;
	wire w_z;
	
	wire [31:0] w_A;
	wire [15:0] w_B;
 
	rsr rsr0 (.clk(clk), .in_B(B) , .shift(w_sh) , .load(w_reset) , .s_B(w_B));
	lsr lsr0 (.clk(clk), .in_A(A) , .shift(w_sh) , .load(w_reset) , .s_A(w_A));

	acc acc0 (.clk(clk), .A(w_A) , .add(w_add), .rst(w_reset), .pp(pp));	
		
	comp comp0(.B(w_B), .z(w_z));
	
	control_mult control0 (.clk(clk), .rst(rst) , .lsb_B(w_B[0]) , .init(init) , .z(w_z) , .done(done) , .sh(w_sh) , .reset(w_reset) , .add(w_add) );
endmodule

hdl/multiplier/mult_32/mult_32_TB.v
`timescale 1ns / 1ps

`define SIMULATION

module mult_32_TB;
	reg  clk;
	reg  rst;
	reg  reset;
	reg  start;
	reg  [15:0] in_A;
	reg  [15:0] in_B;
	wire [31:0] pp;
	wire done;

	mult_32 uut (.clk(clk) , .rst(rst) , .init(start) , .A(in_A) , .B(in_B) , .pp(pp) , .done(done));

	parameter PERIOD 					= 20;
	parameter real DUTY_CYCLE = 0.5;
	parameter OFFSET 					= 0;
	reg [20:0] i;
	event reset_trigger;

	initial begin  // Initialize Inputs
		clk = 0; reset = 1; start = 0; in_A = 16'h0005; in_B = 16'h0003;//in_A = 16'hFA00; in_B = 16'hFA00; //in_A = 8'hAA; in_B = 8'h24;
	end

	initial  begin  // Process for clk
  	#OFFSET;
  	forever
			begin
			clk = 1'b0;
			#(PERIOD-(PERIOD*DUTY_CYCLE)) clk = 1'b1;
			#(PERIOD*DUTY_CYCLE);
		end
	end

	initial begin // Reset the system, Start the image capture process
		forever begin 
			@ (reset_trigger);
			@ (posedge clk);
			start = 0;
			@ (posedge clk);
			start = 1;

			for(i=0; i<2; i=i+1) begin
				@ (posedge clk);
			end
			start = 0;
		end
	end

	initial begin: TEST_CASE
  	$dumpfile("mult_32_TB.vcd");
  	$dumpvars(-1, uut);
	
  	#10 -> reset_trigger;
  	#((PERIOD*DUTY_CYCLE)*120) $finish;
	end
endmodule

hdl/multiplier/mult_32/simulation/mult_32_TB.vcd
$date
	Sat Jun 13 11:01:35 2015
$end
$version
	Icarus Verilog
$end
$timescale
	1ps
$end
$scope module mult_32_TB $end
$scope module uut $end
$var wire 16 ! A [15:0] $end
$var wire 16 " B [15:0] $end
$var wire 1 # clk $end
$var wire 1 $ done $end
$var wire 1 % init $end
$var wire 32 & pp [31:0] $end
$var wire 1 ' rst $end
$var wire 32 ( w_A [31:0] $end
$var wire 16 ) w_B [15:0] $end
$var wire 1 * w_add $end
$var wire 1 + w_reset $end
$var wire 1 , w_sh $end
$var wire 1 - w_z $end
$scope module rsr0 $end
$var wire 1 # clk $end
$var wire 16 . in_B [15:0] $end
$var wire 1 + load $end
$var wire 1 , shift $end
$var reg 16 / s_B [15:0] $end
$upscope $end
$scope module lsr0 $end
$var wire 1 # clk $end
$var wire 16 0 in_A [15:0] $end
$var wire 1 + load $end
$var wire 1 , shift $end
$var reg 31 1 s_A [30:0] $end
$upscope $end
$scope module acc0 $end
$var wire 32 2 A [31:0] $end
$var wire 1 * add $end
$var wire 1 # clk $end
$var wire 1 + rst $end
$var reg 32 3 pp [31:0] $end
$upscope $end
$scope module comp0 $end
$var wire 16 4 B [15:0] $end
$var wire 1 - z $end
$var reg 1 5 tmp $end
$upscope $end
$scope module control0 $end
$var wire 1 # clk $end
$var wire 1 % init $end
$var wire 1 6 lsb_B $end
$var wire 1 ' rst $end
$var wire 1 - z $end
$var reg 1 7 add $end
$var reg 4 8 count [3:0] $end
$var reg 1 9 done $end
$var reg 1 : reset $end
$var reg 1 ; sh $end
$var reg 3 < state [2:0] $end
$upscope $end
$upscope $end
$upscope $end
$enddefinitions $end
#0
$dumpvars
b0 <
0;
1:
09
bx 8
07
16
05
b11 4
b0 3
b101 2
b101 1
b101 0
b11 /
b11 .
0-
0,
1+
0*
b11 )
b101 (
x'
b0 &
0%
0$
0#
b11 "
b101 !
$end
#10000
b0 8
1#
#20000
0#
#30000
1#
#40000
0#
#50000
0:
0+
b1 <
1%
1#
#60000
0#
#70000
17
1*
b11 <
1#
#80000
b101 3
b101 &
0#
#90000
07
0*
1;
1,
b10 <
0%
1#
#100000
b1010 1
b1010 (
b1010 2
b1 /
b1 )
b1 4
0#
#110000
0;
0,
b1 <
1#
#120000
0#
#130000
17
1*
b11 <
1#
#140000
b1111 3
b1111 &
0#
#150000
07
0*
1;
1,
b10 <
1#
#160000
06
15
1-
b0 /
b0 )
b0 4
b10100 1
b10100 (
b10100 2
0#
#170000
0;
0,
19
1$
b100 <
1#
#180000
0#
#190000
b1 8
1#
#200000
0#
#210000
b10 8
1#
#220000
0#
#230000
b11 8
1#
#240000
0#
#250000
b100 8
1#
#260000
0#
#270000
b101 8
1#
#280000
0#
#290000
b110 8
1#
#300000
0#
#310000
b111 8
1#
#320000
0#
#330000
b1000 8
1#
#340000
0#
#350000
b1001 8
1#
#360000
0#
#370000
1:
1+
09
0$
b0 <
b1010 8
1#
#380000
16
05
0-
b0 3
b0 &
b101 1
b101 (
b101 2
b11 /
b11 )
b11 4
0#
#390000
b0 8
1#
